{"ENV_Online Simulation_TotalLoss": 5274.00571627553, "ENV_Online Simulation_TotalLoss_epoch0": 5647.427610505161, "ENV_Online Simulation_Right action": 0.691666891545457, "ENV_Online Simulation_Right action_epoch0": 0.6613493181636939, "ENV_Online Simulation_Probability to choose the right action": 0.5984125549556498, "ENV_Online Simulation_Probability to choose the right action_epoch0": 0.5675173520082727, "ENV_Online Simulation_Weighted right action": 0.6909442895763249, "ENV_Online Simulation_Weighted right action_epoch0": 0.6586729746441038, "ENV_Online Simulation_Weighted probability to choose the right action:": 0.5984256581757822, "ENV_Online Simulation_Weighted probability to choose the right action:_epoch0": 0.5675296141404087, "_timestamp": 1717794587.942626, "_runtime": 6553.470894098282, "_step": 74, "ENV_Train_TotalLoss": 464.4606882688179, "ENV_Train_TotalLoss_epoch0": 531.2805439747225, "ENV_Train_Right action": 0.7833952912019827, "ENV_Train_Right action_epoch0": 0.7414188351920694, "ENV_Train_Probability to choose the right action": 0.7010392983982037, "ENV_Train_Probability to choose the right action_epoch0": 0.6489470635963475, "ENV_Train_Weighted right action": 0.7833952912019827, "ENV_Train_Weighted right action_epoch0": 0.7414188351920694, "ENV_Train_Weighted probability to choose the right action:": 0.7010392983982037, "ENV_Train_Weighted probability to choose the right action:_epoch0": 0.6489470635963475, "ENV_Test_TotalLoss": 124.38368868575489, "ENV_Test_TotalLoss_epoch0": 136.1894974101701, "ENV_Test_Right action": 0.7666810159276797, "ENV_Test_Right action_epoch0": 0.726790070311379, "ENV_Test_Probability to choose the right action": 0.7002283364489619, "ENV_Test_Probability to choose the right action_epoch0": 0.632744605292178, "ENV_Test_Weighted right action": 0.7666810159276797, "ENV_Test_Weighted right action_epoch0": 0.726790070311379, "ENV_Test_Weighted probability to choose the right action:": 0.7002283364489619, "ENV_Test_Weighted probability to choose the right action:_epoch0": 0.632744605292178, "ENV_Test_proba_accuracy": 0.7002283364489614, "ENV_Test_proba_accuracy_epoch0": 0.6327446052921784, "ENV_Test_proba_accuracy_strategy_59": 0.7193363296998149, "ENV_Test_proba_accuracy_strategy_59_epoch0": 0.6479887523434158, "ENV_Test_proba_accuracy_strategy_19": 0.688954489643872, "ENV_Test_proba_accuracy_strategy_19_epoch0": 0.6237504541914486, "ENV_Test_proba_accuracy_per_mean_strategy": 0.7041454096718435, "ENV_Test_proba_accuracy_per_mean_strategy_epoch0": 0.6358696032674321, "ENV_Test_proba_accuracy_per_mean_user": 0.7054179709101033, "ENV_Test_proba_accuracy_per_mean_user_epoch0": 0.6470145892283669, "ENV_Test_proba_accuracy_per_mean_user_and_bot": 0.7205540274817664, "ENV_Test_proba_accuracy_per_mean_user_and_bot_epoch0": 0.6701191153013705, "ENV_Test_accuracy": 0.7666810159276797, "ENV_Test_accuracy_epoch0": 0.726790070311379, "ENV_Test_accuracy_strategy_59": 0.7869296210363496, "ENV_Test_accuracy_strategy_59_epoch0": 0.7412993039443155, "ENV_Test_accuracy_strategy_19": 0.754734200319416, "ENV_Test_accuracy_strategy_19_epoch0": 0.7182295231576545, "ENV_Test_accuracy_per_mean_strategy": 0.7708319106778827, "ENV_Test_accuracy_per_mean_strategy_epoch0": 0.7297644135509851, "ENV_Test_accuracy_per_mean_user": 0.77496199083335, "ENV_Test_accuracy_per_mean_user_epoch0": 0.7462116291241548, "ENV_Test_accuracy_per_mean_user_and_bot": 0.7969726173603259, "ENV_Test_accuracy_per_mean_user_and_bot_epoch0": 0.7742037358247673, "ENV_Online Simulation_TotalLoss_epoch1": 5526.340420994348, "ENV_Online Simulation_Right action_epoch1": 0.6731481481481482, "ENV_Online Simulation_Probability to choose the right action_epoch1": 0.5789379036032825, "ENV_Online Simulation_Weighted right action_epoch1": 0.6709666136042177, "ENV_Online Simulation_Weighted probability to choose the right action:_epoch1": 0.5789460229964531, "ENV_Train_TotalLoss_epoch1": 518.5503297613524, "ENV_Train_Right action_epoch1": 0.7529127416955875, "ENV_Train_Probability to choose the right action_epoch1": 0.6599122891888239, "ENV_Train_Weighted right action_epoch1": 0.7529127416955875, "ENV_Train_Weighted probability to choose the right action:_epoch1": 0.6599122891888239, "ENV_Test_TotalLoss_epoch1": 137.16886005413747, "ENV_Test_Right action_epoch1": 0.7432917204763955, "ENV_Test_Probability to choose the right action_epoch1": 0.6754482839184439, "ENV_Test_Weighted right action_epoch1": 0.7432917204763955, "ENV_Test_Weighted probability to choose the right action:_epoch1": 0.6754482839184439, "ENV_Test_proba_accuracy_epoch1": 0.6754482839184444, "ENV_Test_proba_accuracy_strategy_59_epoch1": 0.6907184648347638, "ENV_Test_proba_accuracy_strategy_19_epoch1": 0.6664387726591239, "ENV_Test_proba_accuracy_per_mean_strategy_epoch1": 0.6785786187469438, "ENV_Test_proba_accuracy_per_mean_user_epoch1": 0.6886678072672356, "ENV_Test_proba_accuracy_per_mean_user_and_bot_epoch1": 0.7130798917492613, "ENV_Test_accuracy_epoch1": 0.7432917204763955, "ENV_Test_accuracy_strategy_59_epoch1": 0.7590873936581594, "ENV_Test_accuracy_strategy_19_epoch1": 0.7339721651836641, "ENV_Test_accuracy_per_mean_strategy_epoch1": 0.7465297794209118, "ENV_Test_accuracy_per_mean_user_epoch1": 0.7547537866776152, "ENV_Test_accuracy_per_mean_user_and_bot_epoch1": 0.7771625607058615, "ENV_Online Simulation_TotalLoss_epoch2": 5349.980484139268, "ENV_Online Simulation_Right action_epoch2": 0.6845671165445054, "ENV_Online Simulation_Probability to choose the right action_epoch2": 0.5895777530687432, "ENV_Online Simulation_Weighted right action_epoch2": 0.6825962203735175, "ENV_Online Simulation_Weighted probability to choose the right action:_epoch2": 0.5895844087503812, "ENV_Train_TotalLoss_epoch2": 513.7636081613675, "ENV_Train_Right action_epoch2": 0.7542451660882499, "ENV_Train_Probability to choose the right action_epoch2": 0.6637095965817265, "ENV_Train_Weighted right action_epoch2": 0.7542451660882499, "ENV_Train_Weighted probability to choose the right action:_epoch2": 0.6637095965817265, "ENV_Test_TotalLoss_epoch2": 132.71009617952808, "ENV_Test_Right action_epoch2": 0.7521882623044913, "ENV_Test_Probability to choose the right action_epoch2": 0.6740860553298609, "ENV_Test_Weighted right action_epoch2": 0.7521882623044913, "ENV_Test_Weighted probability to choose the right action:_epoch2": 0.6740860553298609, "ENV_Test_proba_accuracy_epoch2": 0.6740860553298609, "ENV_Test_proba_accuracy_strategy_59_epoch2": 0.6911130609879392, "ENV_Test_proba_accuracy_strategy_19_epoch2": 0.6640400054480926, "ENV_Test_proba_accuracy_per_mean_strategy_epoch2": 0.6775765332180159, "ENV_Test_proba_accuracy_per_mean_user_epoch2": 0.6871848035695697, "ENV_Test_proba_accuracy_per_mean_user_and_bot_epoch2": 0.7090710143531866, "ENV_Test_accuracy_epoch2": 0.7521882623044913, "ENV_Test_accuracy_strategy_59_epoch2": 0.768754833720031, "ENV_Test_accuracy_strategy_19_epoch2": 0.7424138717773214, "ENV_Test_accuracy_per_mean_strategy_epoch2": 0.7555843527486762, "ENV_Test_accuracy_per_mean_user_epoch2": 0.7655110974546901, "ENV_Test_accuracy_per_mean_user_and_bot_epoch2": 0.7884963001969512, "ENV_Online Simulation_TotalLoss_epoch3": 5422.212460544149, "ENV_Online Simulation_Right action_epoch3": 0.6828617903522572, "ENV_Online Simulation_Probability to choose the right action_epoch3": 0.5883382516732425, "ENV_Online Simulation_Weighted right action_epoch3": 0.680973417310635, "ENV_Online Simulation_Weighted probability to choose the right action:_epoch3": 0.5883527906215479, "ENV_Train_TotalLoss_epoch3": 508.4343033881049, "ENV_Train_Right action_epoch3": 0.7577757125154895, "ENV_Train_Probability to choose the right action_epoch3": 0.6681857134896292, "ENV_Train_Weighted right action_epoch3": 0.7577757125154895, "ENV_Train_Weighted probability to choose the right action:_epoch3": 0.6681857134896292, "ENV_Test_TotalLoss_epoch3": 128.8482212464883, "ENV_Test_Right action_epoch3": 0.7563495479982781, "ENV_Test_Probability to choose the right action_epoch3": 0.6818264857652315, "ENV_Test_Weighted right action_epoch3": 0.7563495479982781, "ENV_Test_Weighted probability to choose the right action:_epoch3": 0.6818264857652315, "ENV_Test_proba_accuracy_epoch3": 0.6818264857652315, "ENV_Test_proba_accuracy_strategy_59_epoch3": 0.6976320405329821, "ENV_Test_proba_accuracy_strategy_19_epoch3": 0.6725011002691326, "ENV_Test_proba_accuracy_per_mean_strategy_epoch3": 0.6850665704010572, "ENV_Test_proba_accuracy_per_mean_user_epoch3": 0.6922009422256649, "ENV_Test_proba_accuracy_per_mean_user_and_bot_epoch3": 0.7126387998466831, "ENV_Test_accuracy_epoch3": 0.7563495479982781, "ENV_Test_accuracy_strategy_59_epoch3": 0.7761020881670534, "ENV_Test_accuracy_strategy_19_epoch3": 0.7446954140999316, "ENV_Test_accuracy_per_mean_strategy_epoch3": 0.7603987511334924, "ENV_Test_accuracy_per_mean_user_epoch3": 0.7671838108637106, "ENV_Test_accuracy_per_mean_user_and_bot_epoch3": 0.7894788049671154, "ENV_Online Simulation_TotalLoss_epoch4": 5535.275904936877, "ENV_Online Simulation_Right action_epoch4": 0.6819612176704292, "ENV_Online Simulation_Probability to choose the right action_epoch4": 0.5886914623100356, "ENV_Online Simulation_Weighted right action_epoch4": 0.680710240891656, "ENV_Online Simulation_Weighted probability to choose the right action:_epoch4": 0.5886967426395731, "ENV_Train_TotalLoss_epoch4": 502.22725127976537, "ENV_Train_Right action_epoch4": 0.7622323448297232, "ENV_Train_Probability to choose the right action_epoch4": 0.6729665351977943, "ENV_Train_Weighted right action_epoch4": 0.7622323448297232, "ENV_Train_Weighted probability to choose the right action:_epoch4": 0.6729665351977943, "ENV_Test_TotalLoss_epoch4": 126.20967616145208, "ENV_Test_Right action_epoch4": 0.7589324149806285, "ENV_Test_Probability to choose the right action_epoch4": 0.6818641240543143, "ENV_Test_Weighted right action_epoch4": 0.7589324149806285, "ENV_Test_Weighted probability to choose the right action:_epoch4": 0.6818641240543143, "ENV_Test_proba_accuracy_epoch4": 0.6818641240543144, "ENV_Test_proba_accuracy_strategy_59_epoch4": 0.6987861200493322, "ENV_Test_proba_accuracy_strategy_19_epoch4": 0.6718800305925037, "ENV_Test_proba_accuracy_per_mean_strategy_epoch4": 0.6853330753209179, "ENV_Test_proba_accuracy_per_mean_user_epoch4": 0.6915623612556164, "ENV_Test_proba_accuracy_per_mean_user_and_bot_epoch4": 0.7105034707121877, "ENV_Test_accuracy_epoch4": 0.7589324149806285, "ENV_Test_accuracy_strategy_59_epoch4": 0.7830626450116009, "ENV_Test_accuracy_strategy_19_epoch4": 0.7446954140999316, "ENV_Test_accuracy_per_mean_strategy_epoch4": 0.7638790295557663, "ENV_Test_accuracy_per_mean_user_epoch4": 0.7694957578636481, "ENV_Test_accuracy_per_mean_user_and_bot_epoch4": 0.7939750576219924, "ENV_Online Simulation_TotalLoss_epoch5": 5454.5179263826385, "ENV_Online Simulation_Right action_epoch5": 0.6838778917243024, "ENV_Online Simulation_Probability to choose the right action_epoch5": 0.5898729502251588, "ENV_Online Simulation_Weighted right action_epoch5": 0.6825305693669604, "ENV_Online Simulation_Weighted probability to choose the right action:_epoch5": 0.5898893367074795, "ENV_Train_TotalLoss_epoch5": 496.9523897819303, "ENV_Train_Right action_epoch5": 0.7660128288556289, "ENV_Train_Probability to choose the right action_epoch5": 0.6781370345803283, "ENV_Train_Weighted right action_epoch5": 0.7660128288556289, "ENV_Train_Weighted probability to choose the right action:_epoch5": 0.6781370345803283, "ENV_Test_TotalLoss_epoch5": 128.22517346779205, "ENV_Test_Right action_epoch5": 0.7628067154541541, "ENV_Test_Probability to choose the right action_epoch5": 0.6884429784897836, "ENV_Test_Weighted right action_epoch5": 0.7628067154541541, "ENV_Test_Weighted probability to choose the right action:_epoch5": 0.6884429784897836, "ENV_Test_proba_accuracy_epoch5": 0.6884429784897843, "ENV_Test_proba_accuracy_strategy_59_epoch5": 0.7087529886726471, "ENV_Test_proba_accuracy_strategy_19_epoch5": 0.6764599334674518, "ENV_Test_proba_accuracy_per_mean_strategy_epoch5": 0.6926064610700495, "ENV_Test_proba_accuracy_per_mean_user_epoch5": 0.697409014027232, "ENV_Test_proba_accuracy_per_mean_user_and_bot_epoch5": 0.7175172187323202, "ENV_Test_accuracy_epoch5": 0.7628067154541541, "ENV_Test_accuracy_strategy_59_epoch5": 0.7834493426140758, "ENV_Test_accuracy_strategy_19_epoch5": 0.7506274241387177, "ENV_Test_accuracy_per_mean_strategy_epoch5": 0.7670383833763967, "ENV_Test_accuracy_per_mean_user_epoch5": 0.7706553788309436, "ENV_Test_accuracy_per_mean_user_and_bot_epoch5": 0.794911398299684, "ENV_Online Simulation_TotalLoss_epoch6": 5494.995905440394, "ENV_Online Simulation_Right action_epoch6": 0.6861492584163855, "ENV_Online Simulation_Probability to choose the right action_epoch6": 0.5917026841199948, "ENV_Online Simulation_Weighted right action_epoch6": 0.6847514977740053, "ENV_Online Simulation_Weighted probability to choose the right action:_epoch6": 0.5917213166054449, "ENV_Train_TotalLoss_epoch6": 489.57892687703156, "ENV_Train_Right action_epoch6": 0.7689876359579808, "ENV_Train_Probability to choose the right action_epoch6": 0.6823508762078677, "ENV_Train_Weighted right action_epoch6": 0.7689876359579808, "ENV_Train_Weighted probability to choose the right action:_epoch6": 0.6823508762078677, "ENV_Test_TotalLoss_epoch6": 129.10570402008, "ENV_Test_Right action_epoch6": 0.7609413115224566, "ENV_Test_Probability to choose the right action_epoch6": 0.6957520446233804, "ENV_Test_Weighted right action_epoch6": 0.7609413115224566, "ENV_Test_Weighted probability to choose the right action:_epoch6": 0.6957520446233804, "ENV_Test_proba_accuracy_epoch6": 0.6957520446233804, "ENV_Test_proba_accuracy_strategy_59_epoch6": 0.7119491800203482, "ENV_Test_proba_accuracy_strategy_19_epoch6": 0.6861956238758194, "ENV_Test_proba_accuracy_per_mean_strategy_epoch6": 0.6990724019480838, "ENV_Test_proba_accuracy_per_mean_user_epoch6": 0.7047019999517922, "ENV_Test_proba_accuracy_per_mean_user_and_bot_epoch6": 0.7234319899972074, "ENV_Test_accuracy_epoch6": 0.7609413115224566, "ENV_Test_accuracy_strategy_59_epoch6": 0.7795823665893271, "ENV_Test_accuracy_strategy_19_epoch6": 0.7499429614419347, "ENV_Test_accuracy_per_mean_strategy_epoch6": 0.7647626640156309, "ENV_Test_accuracy_per_mean_user_epoch6": 0.7770816645995579, "ENV_Test_accuracy_per_mean_user_and_bot_epoch6": 0.8047540730774817, "ENV_Online Simulation_TotalLoss_epoch7": 5439.178977878134, "ENV_Online Simulation_Right action_epoch7": 0.6867683940969931, "ENV_Online Simulation_Probability to choose the right action_epoch7": 0.5929798299874476, "ENV_Online Simulation_Weighted right action_epoch7": 0.6857736110894165, "ENV_Online Simulation_Weighted probability to choose the right action:_epoch7": 0.5929949356752282, "ENV_Train_TotalLoss_epoch7": 487.2959958143386, "ENV_Train_Right action_epoch7": 0.7701341761953456, "ENV_Train_Probability to choose the right action_epoch7": 0.6840272516878811, "ENV_Train_Weighted right action_epoch7": 0.7701341761953456, "ENV_Train_Weighted probability to choose the right action:_epoch7": 0.6840272516878811, "ENV_Test_TotalLoss_epoch7": 125.03407394689691, "ENV_Test_Right action_epoch7": 0.7636676711149376, "ENV_Test_Probability to choose the right action_epoch7": 0.6964114041520344, "ENV_Test_Weighted right action_epoch7": 0.7636676711149376, "ENV_Test_Weighted probability to choose the right action:_epoch7": 0.6964114041520344, "ENV_Test_proba_accuracy_epoch7": 0.6964114041520344, "ENV_Test_proba_accuracy_strategy_59_epoch7": 0.7173732897978187, "ENV_Test_proba_accuracy_strategy_19_epoch7": 0.6840437481447339, "ENV_Test_proba_accuracy_per_mean_strategy_epoch7": 0.7007085189712763, "ENV_Test_proba_accuracy_per_mean_user_epoch7": 0.7028213166170884, "ENV_Test_proba_accuracy_per_mean_user_and_bot_epoch7": 0.7221762099174411, "ENV_Test_accuracy_epoch7": 0.7636676711149376, "ENV_Test_accuracy_strategy_59_epoch7": 0.785769528228925, "ENV_Test_accuracy_strategy_19_epoch7": 0.7506274241387177, "ENV_Test_accuracy_per_mean_strategy_epoch7": 0.7681984761838214, "ENV_Test_accuracy_per_mean_user_epoch7": 0.7772039124702232, "ENV_Test_accuracy_per_mean_user_and_bot_epoch7": 0.8055576783012368, "ENV_Online Simulation_TotalLoss_epoch8": 5389.2961307988535, "ENV_Online Simulation_Right action_epoch8": 0.6868873750894585, "ENV_Online Simulation_Probability to choose the right action_epoch8": 0.5935746735990847, "ENV_Online Simulation_Weighted right action_epoch8": 0.6856140021796047, "ENV_Online Simulation_Weighted probability to choose the right action:_epoch8": 0.5935917377078475, "ENV_Train_TotalLoss_epoch8": 486.9141469176234, "ENV_Train_Right action_epoch8": 0.7702342588001984, "ENV_Train_Probability to choose the right action_epoch8": 0.6855489195367267, "ENV_Train_Weighted right action_epoch8": 0.7702342588001984, "ENV_Train_Weighted probability to choose the right action:_epoch8": 0.6855489195367267, "ENV_Test_TotalLoss_epoch8": 124.78314826707428, "ENV_Test_Right action_epoch8": 0.7618022671832401, "ENV_Test_Probability to choose the right action_epoch8": 0.687132146978708, "ENV_Test_Weighted right action_epoch8": 0.7618022671832401, "ENV_Test_Weighted probability to choose the right action:_epoch8": 0.687132146978708, "ENV_Test_proba_accuracy_epoch8": 0.6871321469787078, "ENV_Test_proba_accuracy_strategy_59_epoch8": 0.7070047867932416, "ENV_Test_proba_accuracy_strategy_19_epoch8": 0.6754071534673267, "ENV_Test_proba_accuracy_per_mean_strategy_epoch8": 0.6912059701302842, "ENV_Test_proba_accuracy_per_mean_user_epoch8": 0.6932528121465479, "ENV_Test_proba_accuracy_per_mean_user_and_bot_epoch8": 0.7115889577931477, "ENV_Test_accuracy_epoch8": 0.7618022671832401, "ENV_Test_accuracy_strategy_59_epoch8": 0.7838360402165506, "ENV_Test_accuracy_strategy_19_epoch8": 0.7488021902806297, "ENV_Test_accuracy_per_mean_strategy_epoch8": 0.7663191152485902, "ENV_Test_accuracy_per_mean_user_epoch8": 0.7742762088379945, "ENV_Test_accuracy_per_mean_user_and_bot_epoch8": 0.7983744115149549, "ENV_Online Simulation_TotalLoss_epoch9": 5331.459027795555, "ENV_Online Simulation_Right action_epoch9": 0.6887972983753025, "ENV_Online Simulation_Probability to choose the right action_epoch9": 0.5959205443648474, "ENV_Online Simulation_Weighted right action_epoch9": 0.6872567775854502, "ENV_Online Simulation_Weighted probability to choose the right action:_epoch9": 0.5959394556382612, "ENV_Train_TotalLoss_epoch9": 480.9422461825988, "ENV_Train_Right action_epoch9": 0.7718384927644015, "ENV_Train_Probability to choose the right action_epoch9": 0.6885977123543736, "ENV_Train_Weighted right action_epoch9": 0.7718384927644015, "ENV_Train_Weighted probability to choose the right action:_epoch9": 0.6885977123543736, "ENV_Test_TotalLoss_epoch9": 126.25142362767569, "ENV_Test_Right action_epoch9": 0.7606543263021954, "ENV_Test_Probability to choose the right action_epoch9": 0.6890046229482782, "ENV_Test_Weighted right action_epoch9": 0.7606543263021954, "ENV_Test_Weighted probability to choose the right action:_epoch9": 0.6890046229482782, "ENV_Test_proba_accuracy_epoch9": 0.6890046229482786, "ENV_Test_proba_accuracy_strategy_59_epoch9": 0.7051088906402769, "ENV_Test_proba_accuracy_strategy_19_epoch9": 0.6795029947822946, "ENV_Test_proba_accuracy_per_mean_strategy_epoch9": 0.6923059427112858, "ENV_Test_proba_accuracy_per_mean_user_epoch9": 0.6950337647703262, "ENV_Test_proba_accuracy_per_mean_user_and_bot_epoch9": 0.7120169144682017, "ENV_Test_accuracy_epoch9": 0.7606543263021954, "ENV_Test_accuracy_strategy_59_epoch9": 0.7726218097447796, "ENV_Test_accuracy_strategy_19_epoch9": 0.7535934291581109, "ENV_Test_accuracy_per_mean_strategy_epoch9": 0.7631076194514452, "ENV_Test_accuracy_per_mean_user_epoch9": 0.7694768381143203, "ENV_Test_accuracy_per_mean_user_and_bot_epoch9": 0.796255570609844, "ENV_Online Simulation_TotalLoss_epoch10": 5353.668668401022, "ENV_Online Simulation_Right action_epoch10": 0.6889718629150553, "ENV_Online Simulation_Probability to choose the right action_epoch10": 0.5947356847490443, "ENV_Online Simulation_Weighted right action_epoch10": 0.6879847409830215, "ENV_Online Simulation_Weighted probability to choose the right action:_epoch10": 0.5947510144005738, "ENV_Train_TotalLoss_epoch10": 480.2166100810144, "ENV_Train_Right action_epoch10": 0.7722723188001611, "ENV_Train_Probability to choose the right action_epoch10": 0.6897493370630946, "ENV_Train_Weighted right action_epoch10": 0.7722723188001611, "ENV_Train_Weighted probability to choose the right action:_epoch10": 0.6897493370630946, "ENV_Test_TotalLoss_epoch10": 124.73554765953598, "ENV_Test_Right action_epoch10": 0.759793370641412, "ENV_Test_Probability to choose the right action_epoch10": 0.6856535020058309, "ENV_Test_Weighted right action_epoch10": 0.759793370641412, "ENV_Test_Weighted probability to choose the right action:_epoch10": 0.6856535020058309, "ENV_Test_proba_accuracy_epoch10": 0.6856535020058311, "ENV_Test_proba_accuracy_strategy_59_epoch10": 0.7033396917437238, "ENV_Test_proba_accuracy_strategy_19_epoch10": 0.6752185290051033, "ENV_Test_proba_accuracy_per_mean_strategy_epoch10": 0.6892791103744135, "ENV_Test_proba_accuracy_per_mean_user_epoch10": 0.6910707095678481, "ENV_Test_proba_accuracy_per_mean_user_and_bot_epoch10": 0.7080544608354786, "ENV_Test_accuracy_epoch10": 0.759793370641412, "ENV_Test_accuracy_strategy_59_epoch10": 0.782675947409126, "ENV_Test_accuracy_strategy_19_epoch10": 0.7462924937257586, "ENV_Test_accuracy_per_mean_strategy_epoch10": 0.7644842205674423, "ENV_Test_accuracy_per_mean_user_epoch10": 0.7692432982646074, "ENV_Test_accuracy_per_mean_user_and_bot_epoch10": 0.798469308374815, "ENV_Online Simulation_TotalLoss_epoch11": 5420.61270641135, "ENV_Online Simulation_Right action_epoch11": 0.6883843605036448, "ENV_Online Simulation_Probability to choose the right action_epoch11": 0.5958876853893122, "ENV_Online Simulation_Weighted right action_epoch11": 0.6876853941135113, "ENV_Online Simulation_Weighted probability to choose the right action:_epoch11": 0.5959080005837896, "ENV_Train_TotalLoss_epoch11": 478.82655283450214, "ENV_Train_Right action_epoch11": 0.7748621352004461, "ENV_Train_Probability to choose the right action_epoch11": 0.6916064900556796, "ENV_Train_Weighted right action_epoch11": 0.7748621352004461, "ENV_Train_Weighted probability to choose the right action:_epoch11": 0.6916064900556796, "ENV_Test_TotalLoss_epoch11": 125.72542684507923, "ENV_Test_Right action_epoch11": 0.7640981489453293, "ENV_Test_Probability to choose the right action_epoch11": 0.694925604106655, "ENV_Test_Weighted right action_epoch11": 0.7640981489453293, "ENV_Test_Weighted probability to choose the right action:_epoch11": 0.694925604106655, "ENV_Test_proba_accuracy_epoch11": 0.6949256041066548, "ENV_Test_proba_accuracy_strategy_59_epoch11": 0.7143988524109088, "ENV_Test_proba_accuracy_strategy_19_epoch11": 0.6834362543200245, "ENV_Test_proba_accuracy_per_mean_strategy_epoch11": 0.6989175533654667, "ENV_Test_proba_accuracy_per_mean_user_epoch11": 0.7002265416637489, "ENV_Test_proba_accuracy_per_mean_user_and_bot_epoch11": 0.7174371234116248, "ENV_Test_accuracy_epoch11": 0.7640981489453293, "ENV_Test_accuracy_strategy_59_epoch11": 0.7873163186388245, "ENV_Test_accuracy_strategy_19_epoch11": 0.7503992699064568, "ENV_Test_accuracy_per_mean_strategy_epoch11": 0.7688577942726407, "ENV_Test_accuracy_per_mean_user_epoch11": 0.7751149345474769, "ENV_Test_accuracy_per_mean_user_and_bot_epoch11": 0.8017429625851403, "ENV_Online Simulation_TotalLoss_epoch12": 5489.536878690736, "ENV_Online Simulation_Right action_epoch12": 0.6862505558898161, "ENV_Online Simulation_Probability to choose the right action_epoch12": 0.5917334633372503, "ENV_Online Simulation_Weighted right action_epoch12": 0.6852646257540513, "ENV_Online Simulation_Weighted probability to choose the right action:_epoch12": 0.5917503791679809, "ENV_Train_TotalLoss_epoch12": 477.85239002484866, "ENV_Train_Right action_epoch12": 0.7737608426270136, "ENV_Train_Probability to choose the right action_epoch12": 0.6914942354892021, "ENV_Train_Weighted right action_epoch12": 0.7737608426270136, "ENV_Train_Weighted probability to choose the right action:_epoch12": 0.6914942354892021, "ENV_Test_TotalLoss_epoch12": 125.38638875393316, "ENV_Test_Right action_epoch12": 0.7642416415554599, "ENV_Test_Probability to choose the right action_epoch12": 0.6942849434643145, "ENV_Test_Weighted right action_epoch12": 0.7642416415554599, "ENV_Test_Weighted probability to choose the right action:_epoch12": 0.6942849434643145, "ENV_Test_proba_accuracy_epoch12": 0.6942849434643141, "ENV_Test_proba_accuracy_strategy_59_epoch12": 0.7144056302984405, "ENV_Test_proba_accuracy_strategy_19_epoch12": 0.682413600513584, "ENV_Test_proba_accuracy_per_mean_strategy_epoch12": 0.6984096154060122, "ENV_Test_proba_accuracy_per_mean_user_epoch12": 0.6991583135349412, "ENV_Test_proba_accuracy_per_mean_user_and_bot_epoch12": 0.7183798655841006, "ENV_Test_accuracy_epoch12": 0.7642416415554599, "ENV_Test_accuracy_strategy_59_epoch12": 0.7849961330239753, "ENV_Test_accuracy_strategy_19_epoch12": 0.7519963495322838, "ENV_Test_accuracy_per_mean_strategy_epoch12": 0.7684962412781295, "ENV_Test_accuracy_per_mean_user_epoch12": 0.7704273997700174, "ENV_Test_accuracy_per_mean_user_and_bot_epoch12": 0.7986788984455926, "ENV_Online Simulation_TotalLoss_epoch13": 5353.461673183993, "ENV_Online Simulation_Right action_epoch13": 0.6888534947306947, "ENV_Online Simulation_Probability to choose the right action_epoch13": 0.5952080533928918, "ENV_Online Simulation_Weighted right action_epoch13": 0.6877915879229816, "ENV_Online Simulation_Weighted probability to choose the right action:_epoch13": 0.5952321182427752, "ENV_Train_TotalLoss_epoch13": 476.18088685007604, "ENV_Train_Right action_epoch13": 0.7757675268750581, "ENV_Train_Probability to choose the right action_epoch13": 0.6936626753425427, "ENV_Train_Weighted right action_epoch13": 0.7757675268750581, "ENV_Train_Weighted probability to choose the right action:_epoch13": 0.6936626753425427, "ENV_Test_TotalLoss_epoch13": 123.81298422076334, "ENV_Test_Right action_epoch13": 0.7596498780312814, "ENV_Test_Probability to choose the right action_epoch13": 0.6759388513476501, "ENV_Test_Weighted right action_epoch13": 0.7596498780312814, "ENV_Test_Weighted probability to choose the right action:_epoch13": 0.6759388513476501, "ENV_Test_proba_accuracy_epoch13": 0.6759388513476503, "ENV_Test_proba_accuracy_strategy_59_epoch13": 0.6950456710330111, "ENV_Test_proba_accuracy_strategy_19_epoch13": 0.6646656969542342, "ENV_Test_proba_accuracy_per_mean_strategy_epoch13": 0.6798556839936226, "ENV_Test_proba_accuracy_per_mean_user_epoch13": 0.6805737590579234, "ENV_Test_proba_accuracy_per_mean_user_and_bot_epoch13": 0.6957650119793227, "ENV_Test_accuracy_epoch13": 0.7596498780312814, "ENV_Test_accuracy_strategy_59_epoch13": 0.7819025522041764, "ENV_Test_accuracy_strategy_19_epoch13": 0.7465206479580196, "ENV_Test_accuracy_per_mean_strategy_epoch13": 0.764211600081098, "ENV_Test_accuracy_per_mean_user_epoch13": 0.7681240636025848, "ENV_Test_accuracy_per_mean_user_and_bot_epoch13": 0.7965958267433864, "ENV_Online Simulation_TotalLoss_epoch14": 5485.678516830558, "ENV_Online Simulation_Right action_epoch14": 0.6872322013897993, "ENV_Online Simulation_Probability to choose the right action_epoch14": 0.5928098227995509, "ENV_Online Simulation_Weighted right action_epoch14": 0.6863953732511936, "ENV_Online Simulation_Weighted probability to choose the right action:_epoch14": 0.5928297462625228, "ENV_Train_TotalLoss_epoch14": 473.37833265095605, "ENV_Train_Right action_epoch14": 0.7742874845105329, "ENV_Train_Probability to choose the right action_epoch14": 0.6954957431985809, "ENV_Train_Weighted right action_epoch14": 0.7742874845105329, "ENV_Train_Weighted probability to choose the right action:_epoch14": 0.6954957431985809, "ENV_Test_TotalLoss_epoch14": 124.04479739125821, "ENV_Test_Right action_epoch14": 0.7567800258286699, "ENV_Test_Probability to choose the right action_epoch14": 0.6847163919206452, "ENV_Test_Weighted right action_epoch14": 0.7567800258286699, "ENV_Test_Weighted probability to choose the right action:_epoch14": 0.6847163919206452, "ENV_Test_proba_accuracy_epoch14": 0.6847163919206448, "ENV_Test_proba_accuracy_strategy_59_epoch14": 0.7023460361792541, "ENV_Test_proba_accuracy_strategy_19_epoch14": 0.6743147811397268, "ENV_Test_proba_accuracy_per_mean_strategy_epoch14": 0.6883304086594904, "ENV_Test_proba_accuracy_per_mean_user_epoch14": 0.6910372169289329, "ENV_Test_proba_accuracy_per_mean_user_and_bot_epoch14": 0.7071258080082677, "ENV_Test_accuracy_epoch14": 0.7567800258286699, "ENV_Test_accuracy_strategy_59_epoch14": 0.7791956689868523, "ENV_Test_accuracy_strategy_19_epoch14": 0.7435546429386265, "ENV_Test_accuracy_per_mean_strategy_epoch14": 0.7613751559627394, "ENV_Test_accuracy_per_mean_user_epoch14": 0.7655344999023606, "ENV_Test_accuracy_per_mean_user_and_bot_epoch14": 0.7897481207599866, "ENV_Online Simulation_TotalLoss_epoch15": 5224.5766246153435, "ENV_Online Simulation_Right action_epoch15": 0.6944766735921859, "ENV_Online Simulation_Probability to choose the right action_epoch15": 0.6001642387981736, "ENV_Online Simulation_Weighted right action_epoch15": 0.6933360881025651, "ENV_Online Simulation_Weighted probability to choose the right action:_epoch15": 0.60018013853366, "ENV_Train_TotalLoss_epoch15": 474.7483579463415, "ENV_Train_Right action_epoch15": 0.7738526850732856, "ENV_Train_Probability to choose the right action_epoch15": 0.694483178715882, "ENV_Train_Weighted right action_epoch15": 0.7738526850732856, "ENV_Train_Weighted probability to choose the right action:_epoch15": 0.694483178715882, "ENV_Test_TotalLoss_epoch15": 123.52639773289812, "ENV_Test_Right action_epoch15": 0.7585019371502367, "ENV_Test_Probability to choose the right action_epoch15": 0.6924511045681105, "ENV_Test_Weighted right action_epoch15": 0.7585019371502367, "ENV_Test_Weighted probability to choose the right action:_epoch15": 0.6924511045681105, "ENV_Test_proba_accuracy_epoch15": 0.6924511045681107, "ENV_Test_proba_accuracy_strategy_59_epoch15": 0.7108364376162568, "ENV_Test_proba_accuracy_strategy_19_epoch15": 0.6816036322289579, "ENV_Test_proba_accuracy_per_mean_strategy_epoch15": 0.6962200349226074, "ENV_Test_proba_accuracy_per_mean_user_epoch15": 0.6967017058443075, "ENV_Test_proba_accuracy_per_mean_user_and_bot_epoch15": 0.7130494339529829, "ENV_Test_accuracy_epoch15": 0.7585019371502367, "ENV_Test_accuracy_strategy_59_epoch15": 0.7791956689868523, "ENV_Test_accuracy_strategy_19_epoch15": 0.7462924937257586, "ENV_Test_accuracy_per_mean_strategy_epoch15": 0.7627440813563054, "ENV_Test_accuracy_per_mean_user_epoch15": 0.7631644169879115, "ENV_Test_accuracy_per_mean_user_and_bot_epoch15": 0.7877546022078835, "ENV_Online Simulation_TotalLoss_epoch16": 5463.721211519117, "ENV_Online Simulation_Right action_epoch16": 0.6867779474487915, "ENV_Online Simulation_Probability to choose the right action_epoch16": 0.5936696461064853, "ENV_Online Simulation_Weighted right action_epoch16": 0.6859760757752059, "ENV_Online Simulation_Weighted probability to choose the right action:_epoch16": 0.5936837798944362, "ENV_Train_TotalLoss_epoch16": 473.1176153992674, "ENV_Train_Right action_epoch16": 0.7784386617100372, "ENV_Train_Probability to choose the right action_epoch16": 0.6966168561662867, "ENV_Train_Weighted right action_epoch16": 0.7784386617100372, "ENV_Train_Weighted probability to choose the right action:_epoch16": 0.6966168561662867, "ENV_Test_TotalLoss_epoch16": 123.71715915042736, "ENV_Test_Right action_epoch16": 0.7619457597933706, "ENV_Test_Probability to choose the right action_epoch16": 0.6967669009330539, "ENV_Test_Weighted right action_epoch16": 0.7619457597933706, "ENV_Test_Weighted probability to choose the right action:_epoch16": 0.6967669009330539, "ENV_Test_proba_accuracy_epoch16": 0.6967669009330539, "ENV_Test_proba_accuracy_strategy_59_epoch16": 0.7155308573354319, "ENV_Test_proba_accuracy_strategy_19_epoch16": 0.6856960382233689, "ENV_Test_proba_accuracy_per_mean_strategy_epoch16": 0.7006134477794004, "ENV_Test_proba_accuracy_per_mean_user_epoch16": 0.7040036244858145, "ENV_Test_proba_accuracy_per_mean_user_and_bot_epoch16": 0.7211290581103179, "ENV_Test_accuracy_epoch16": 0.7619457597933706, "ENV_Test_accuracy_strategy_59_epoch16": 0.7842227378190255, "ENV_Test_accuracy_strategy_19_epoch16": 0.7488021902806297, "ENV_Test_accuracy_per_mean_strategy_epoch16": 0.7665124640498275, "ENV_Test_accuracy_per_mean_user_epoch16": 0.7741518121922171, "ENV_Test_accuracy_per_mean_user_and_bot_epoch16": 0.7987644694244838, "ENV_Online Simulation_TotalLoss_epoch17": 5369.334096141434, "ENV_Online Simulation_Right action_epoch17": 0.6897678006223901, "ENV_Online Simulation_Probability to choose the right action_epoch17": 0.595820528839713, "ENV_Online Simulation_Weighted right action_epoch17": 0.6889743619029706, "ENV_Online Simulation_Weighted probability to choose the right action:_epoch17": 0.5958320731179554, "ENV_Train_TotalLoss_epoch17": 473.4680534354138, "ENV_Train_Right action_epoch17": 0.7753710761984445, "ENV_Train_Probability to choose the right action_epoch17": 0.6947826791690049, "ENV_Train_Weighted right action_epoch17": 0.7753710761984445, "ENV_Train_Weighted probability to choose the right action:_epoch17": 0.6947826791690049, "ENV_Test_TotalLoss_epoch17": 124.40346288908293, "ENV_Test_Right action_epoch17": 0.7695508681302913, "ENV_Test_Probability to choose the right action_epoch17": 0.7014333113884312, "ENV_Test_Weighted right action_epoch17": 0.7695508681302913, "ENV_Test_Weighted probability to choose the right action:_epoch17": 0.7014333113884312, "ENV_Test_proba_accuracy_epoch17": 0.7014333113884309, "ENV_Test_proba_accuracy_strategy_59_epoch17": 0.720918622139304, "ENV_Test_proba_accuracy_strategy_19_epoch17": 0.6899368446757325, "ENV_Test_proba_accuracy_per_mean_strategy_epoch17": 0.7054277334075183, "ENV_Test_proba_accuracy_per_mean_user_epoch17": 0.7075575252360208, "ENV_Test_proba_accuracy_per_mean_user_and_bot_epoch17": 0.7240380575234624, "ENV_Test_accuracy_epoch17": 0.7695508681302913, "ENV_Test_accuracy_strategy_59_epoch17": 0.794276875483372, "ENV_Test_accuracy_strategy_19_epoch17": 0.7549623545516769, "ENV_Test_accuracy_per_mean_strategy_epoch17": 0.7746196150175244, "ENV_Test_accuracy_per_mean_user_epoch17": 0.7782096871735726, "ENV_Test_accuracy_per_mean_user_and_bot_epoch17": 0.8027025546140568, "ENV_Online Simulation_TotalLoss_epoch18": 5450.371794985101, "ENV_Online Simulation_Right action_epoch18": 0.6892144967292678, "ENV_Online Simulation_Probability to choose the right action_epoch18": 0.5959486185617479, "ENV_Online Simulation_Weighted right action_epoch18": 0.6886972327007004, "ENV_Online Simulation_Weighted probability to choose the right action:_epoch18": 0.5959660960187457, "ENV_Train_TotalLoss_epoch18": 470.72940838994106, "ENV_Train_Right action_epoch18": 0.7776641883519207, "ENV_Train_Probability to choose the right action_epoch18": 0.6964493936245282, "ENV_Train_Weighted right action_epoch18": 0.7776641883519207, "ENV_Train_Weighted probability to choose the right action:_epoch18": 0.6964493936245282, "ENV_Test_TotalLoss_epoch18": 123.64096842959515, "ENV_Test_Right action_epoch18": 0.763524178504807, "ENV_Test_Probability to choose the right action_epoch18": 0.697952896792332, "ENV_Test_Weighted right action_epoch18": 0.763524178504807, "ENV_Test_Weighted probability to choose the right action:_epoch18": 0.697952896792332, "ENV_Test_proba_accuracy_epoch18": 0.6979528967923323, "ENV_Test_proba_accuracy_strategy_59_epoch18": 0.7161231965051568, "ENV_Test_proba_accuracy_strategy_19_epoch18": 0.6872322955928424, "ENV_Test_proba_accuracy_per_mean_strategy_epoch18": 0.7016777460489996, "ENV_Test_proba_accuracy_per_mean_user_epoch18": 0.7046303978415565, "ENV_Test_proba_accuracy_per_mean_user_and_bot_epoch18": 0.7206967715207078, "ENV_Test_accuracy_epoch18": 0.763524178504807, "ENV_Test_accuracy_strategy_59_epoch18": 0.7834493426140758, "ENV_Test_accuracy_strategy_19_epoch18": 0.7517681953000228, "ENV_Test_accuracy_per_mean_strategy_epoch18": 0.7676087689570493, "ENV_Test_accuracy_per_mean_user_epoch18": 0.7758050370903411, "ENV_Test_accuracy_per_mean_user_and_bot_epoch18": 0.7951546218023078, "ENV_Online Simulation_TotalLoss_epoch19": 5369.931841681518, "ENV_Online Simulation_Right action_epoch19": 0.6887036397907983, "ENV_Online Simulation_Probability to choose the right action_epoch19": 0.5956447110202986, "ENV_Online Simulation_Weighted right action_epoch19": 0.6881088994180012, "ENV_Online Simulation_Weighted probability to choose the right action:_epoch19": 0.5956586725165303, "ENV_Train_TotalLoss_epoch19": 472.0841203956542, "ENV_Train_Right action_epoch19": 0.7780050199869852, "ENV_Train_Probability to choose the right action_epoch19": 0.6972246209413283, "ENV_Train_Weighted right action_epoch19": 0.7780050199869852, "ENV_Train_Weighted probability to choose the right action:_epoch19": 0.6972246209413283, "ENV_Test_TotalLoss_epoch19": 125.76523668049069, "ENV_Test_Right action_epoch19": 0.7669680011479408, "ENV_Test_Probability to choose the right action_epoch19": 0.7061979753014964, "ENV_Test_Weighted right action_epoch19": 0.7669680011479408, "ENV_Test_Weighted probability to choose the right action:_epoch19": 0.7061979753014964, "ENV_Test_proba_accuracy_epoch19": 0.7061979753014963, "ENV_Test_proba_accuracy_strategy_59_epoch19": 0.7211444571101278, "ENV_Test_proba_accuracy_strategy_19_epoch19": 0.697379448731311, "ENV_Test_proba_accuracy_per_mean_strategy_epoch19": 0.7092619529207195, "ENV_Test_proba_accuracy_per_mean_user_epoch19": 0.7139641423144337, "ENV_Test_proba_accuracy_per_mean_user_and_bot_epoch19": 0.7304091067434666, "ENV_Test_accuracy_epoch19": 0.7669680011479408, "ENV_Test_accuracy_strategy_59_epoch19": 0.7822892498066512, "ENV_Test_accuracy_strategy_19_epoch19": 0.7579283595710701, "ENV_Test_accuracy_per_mean_strategy_epoch19": 0.7701088046888607, "ENV_Test_accuracy_per_mean_user_epoch19": 0.776632142171246, "ENV_Test_accuracy_per_mean_user_and_bot_epoch19": 0.7988786409953098, "ENV_Online Simulation_TotalLoss_epoch20": 5409.259420031529, "ENV_Online Simulation_Right action_epoch20": 0.6885545691350805, "ENV_Online Simulation_Probability to choose the right action_epoch20": 0.5951380685758642, "ENV_Online Simulation_Weighted right action_epoch20": 0.6879768825378565, "ENV_Online Simulation_Weighted probability to choose the right action:_epoch20": 0.5951545848887504, "ENV_Train_TotalLoss_epoch20": 472.963867790814, "ENV_Train_Right action_epoch20": 0.778407858448762, "ENV_Train_Probability to choose the right action_epoch20": 0.6965696605428848, "ENV_Train_Weighted right action_epoch20": 0.778407858448762, "ENV_Train_Weighted probability to choose the right action:_epoch20": 0.6965696605428848, "ENV_Test_TotalLoss_epoch20": 122.88467581923301, "ENV_Test_Right action_epoch20": 0.7709857942315971, "ENV_Test_Probability to choose the right action_epoch20": 0.7000662228159035, "ENV_Test_Weighted right action_epoch20": 0.7709857942315971, "ENV_Test_Weighted probability to choose the right action:_epoch20": 0.7000662228159035, "ENV_Test_proba_accuracy_epoch20": 0.7000662228159036, "ENV_Test_proba_accuracy_strategy_59_epoch20": 0.7164073472473832, "ENV_Test_proba_accuracy_strategy_19_epoch20": 0.6904248475524295, "ENV_Test_proba_accuracy_per_mean_strategy_epoch20": 0.7034160973999064, "ENV_Test_proba_accuracy_per_mean_user_epoch20": 0.7062504367105159, "ENV_Test_proba_accuracy_per_mean_user_and_bot_epoch20": 0.7209649788027964, "ENV_Test_accuracy_epoch20": 0.7709857942315971, "ENV_Test_accuracy_strategy_59_epoch20": 0.7888631090487239, "ENV_Test_accuracy_strategy_19_epoch20": 0.7604380561259412, "ENV_Test_accuracy_per_mean_strategy_epoch20": 0.7746505825873325, "ENV_Test_accuracy_per_mean_user_epoch20": 0.779473314633461, "ENV_Test_accuracy_per_mean_user_and_bot_epoch20": 0.807651632238251, "ENV_Online Simulation_TotalLoss_epoch21": 5408.210634552478, "ENV_Online Simulation_Right action_epoch21": 0.6894363421363816, "ENV_Online Simulation_Probability to choose the right action_epoch21": 0.5949780443580005, "ENV_Online Simulation_Weighted right action_epoch21": 0.6882979294357275, "ENV_Online Simulation_Weighted probability to choose the right action:_epoch21": 0.5950006021940113, "ENV_Train_TotalLoss_epoch21": 465.95572413361174, "ENV_Train_Right action_epoch21": 0.7787487217625733, "ENV_Train_Probability to choose the right action_epoch21": 0.7000764634042491, "ENV_Train_Weighted right action_epoch21": 0.7787487217625733, "ENV_Train_Weighted probability to choose the right action:_epoch21": 0.7000764634042491, "ENV_Test_TotalLoss_epoch21": 125.1937916635637, "ENV_Test_Right action_epoch21": 0.7692638829100301, "ENV_Test_Probability to choose the right action_epoch21": 0.710093104382728, "ENV_Test_Weighted right action_epoch21": 0.7692638829100301, "ENV_Test_Weighted probability to choose the right action:_epoch21": 0.710093104382728, "ENV_Test_proba_accuracy_epoch21": 0.7100931043827272, "ENV_Test_proba_accuracy_strategy_59_epoch21": 0.7301609016422168, "ENV_Test_proba_accuracy_strategy_19_epoch21": 0.6982529666430421, "ENV_Test_proba_accuracy_per_mean_strategy_epoch21": 0.7142069341426295, "ENV_Test_proba_accuracy_per_mean_user_epoch21": 0.7166294407151362, "ENV_Test_proba_accuracy_per_mean_user_and_bot_epoch21": 0.7325288574018795, "ENV_Test_accuracy_epoch21": 0.7692638829100301, "ENV_Test_accuracy_strategy_59_epoch21": 0.7869296210363496, "ENV_Test_accuracy_strategy_19_epoch21": 0.7588409765001141, "ENV_Test_accuracy_per_mean_strategy_epoch21": 0.7728852987682318, "ENV_Test_accuracy_per_mean_user_epoch21": 0.7826920586137273, "ENV_Test_accuracy_per_mean_user_and_bot_epoch21": 0.805603725302634, "ENV_Online Simulation_TotalLoss_epoch22": 5401.887454514218, "ENV_Online Simulation_Right action_epoch22": 0.6895317316891676, "ENV_Online Simulation_Probability to choose the right action_epoch22": 0.5963818528123215, "ENV_Online Simulation_Weighted right action_epoch22": 0.6887481082633582, "ENV_Online Simulation_Weighted probability to choose the right action:_epoch22": 0.5963941876418773, "ENV_Train_TotalLoss_epoch22": 468.01862182871207, "ENV_Train_Right action_epoch22": 0.7784766980664353, "ENV_Train_Probability to choose the right action_epoch22": 0.7000855376584664, "ENV_Train_Weighted right action_epoch22": 0.7784766980664353, "ENV_Train_Weighted probability to choose the right action:_epoch22": 0.7000855376584664, "ENV_Test_TotalLoss_epoch22": 123.39678725383051, "ENV_Test_Right action_epoch22": 0.7585019371502367, "ENV_Test_Probability to choose the right action_epoch22": 0.6875504613221769, "ENV_Test_Weighted right action_epoch22": 0.7585019371502367, "ENV_Test_Weighted probability to choose the right action:_epoch22": 0.6875504613221769, "ENV_Test_proba_accuracy_epoch22": 0.6875504613221765, "ENV_Test_proba_accuracy_strategy_59_epoch22": 0.7060519387993973, "ENV_Test_proba_accuracy_strategy_19_epoch22": 0.6766344629749047, "ENV_Test_proba_accuracy_per_mean_strategy_epoch22": 0.691343200887151, "ENV_Test_proba_accuracy_per_mean_user_epoch22": 0.6922440737416418, "ENV_Test_proba_accuracy_per_mean_user_and_bot_epoch22": 0.7044831487244432, "ENV_Test_accuracy_epoch22": 0.7585019371502367, "ENV_Test_accuracy_strategy_59_epoch22": 0.777262180974478, "ENV_Test_accuracy_strategy_19_epoch22": 0.7474332648870636, "ENV_Test_accuracy_per_mean_strategy_epoch22": 0.7623477229307708, "ENV_Test_accuracy_per_mean_user_epoch22": 0.7711469494296097, "ENV_Test_accuracy_per_mean_user_and_bot_epoch22": 0.7944063655540781, "ENV_Online Simulation_TotalLoss_epoch23": 5165.281181957924, "ENV_Online Simulation_Right action_epoch23": 0.6927996483613088, "ENV_Online Simulation_Probability to choose the right action_epoch23": 0.5996487316486412, "ENV_Online Simulation_Weighted right action_epoch23": 0.691979301396534, "ENV_Online Simulation_Weighted probability to choose the right action:_epoch23": 0.5996693644083245, "ENV_Train_TotalLoss_epoch23": 466.5182805261415, "ENV_Train_Right action_epoch23": 0.7789000774593339, "ENV_Train_Probability to choose the right action_epoch23": 0.7009696647976457, "ENV_Train_Weighted right action_epoch23": 0.7789000774593339, "ENV_Train_Weighted probability to choose the right action:_epoch23": 0.7009696647976457, "ENV_Test_TotalLoss_epoch23": 124.62922791772624, "ENV_Test_Right action_epoch23": 0.7609413115224566, "ENV_Test_Probability to choose the right action_epoch23": 0.6980250691029665, "ENV_Test_Weighted right action_epoch23": 0.7609413115224566, "ENV_Test_Weighted probability to choose the right action:_epoch23": 0.6980250691029665, "ENV_Test_proba_accuracy_epoch23": 0.6980250691029664, "ENV_Test_proba_accuracy_strategy_59_epoch23": 0.715567328541638, "ENV_Test_proba_accuracy_strategy_19_epoch23": 0.6876750159639281, "ENV_Test_proba_accuracy_per_mean_strategy_epoch23": 0.701621172252783, "ENV_Test_proba_accuracy_per_mean_user_epoch23": 0.7046304499838348, "ENV_Test_proba_accuracy_per_mean_user_and_bot_epoch23": 0.7192015177190781, "ENV_Test_accuracy_epoch23": 0.7609413115224566, "ENV_Test_accuracy_strategy_59_epoch23": 0.779969064191802, "ENV_Test_accuracy_strategy_19_epoch23": 0.7497148072096738, "ENV_Test_accuracy_per_mean_strategy_epoch23": 0.7648419357007379, "ENV_Test_accuracy_per_mean_user_epoch23": 0.7727650139318388, "ENV_Test_accuracy_per_mean_user_and_bot_epoch23": 0.7973548468584679, "ENV_Online Simulation_TotalLoss_epoch24": 5274.00571627553, "ENV_Online Simulation_Right action_epoch24": 0.691666891545457, "ENV_Online Simulation_Probability to choose the right action_epoch24": 0.5984125549556498, "ENV_Online Simulation_Weighted right action_epoch24": 0.6909442895763249, "ENV_Online Simulation_Weighted probability to choose the right action:_epoch24": 0.5984256581757822, "ENV_Train_TotalLoss_epoch24": 464.4606882688179, "ENV_Train_Right action_epoch24": 0.7833952912019827, "ENV_Train_Probability to choose the right action_epoch24": 0.7010392983982037, "ENV_Train_Weighted right action_epoch24": 0.7833952912019827, "ENV_Train_Weighted probability to choose the right action:_epoch24": 0.7010392983982037, "ENV_Test_TotalLoss_epoch24": 124.38368868575489, "ENV_Test_Right action_epoch24": 0.7666810159276797, "ENV_Test_Probability to choose the right action_epoch24": 0.7002283364489619, "ENV_Test_Weighted right action_epoch24": 0.7666810159276797, "ENV_Test_Weighted probability to choose the right action:_epoch24": 0.7002283364489619, "ENV_Test_proba_accuracy_epoch24": 0.7002283364489614, "ENV_Test_proba_accuracy_strategy_59_epoch24": 0.7193363296998149, "ENV_Test_proba_accuracy_strategy_19_epoch24": 0.688954489643872, "ENV_Test_proba_accuracy_per_mean_strategy_epoch24": 0.7041454096718435, "ENV_Test_proba_accuracy_per_mean_user_epoch24": 0.7054179709101033, "ENV_Test_proba_accuracy_per_mean_user_and_bot_epoch24": 0.7205540274817664, "ENV_Test_accuracy_epoch24": 0.7666810159276797, "ENV_Test_accuracy_strategy_59_epoch24": 0.7869296210363496, "ENV_Test_accuracy_strategy_19_epoch24": 0.754734200319416, "ENV_Test_accuracy_per_mean_strategy_epoch24": 0.7708319106778827, "ENV_Test_accuracy_per_mean_user_epoch24": 0.77496199083335, "ENV_Test_accuracy_per_mean_user_and_bot_epoch24": 0.7969726173603259, "_wandb": {"runtime": 6553}}