{"ENV_Online Simulation_TotalLoss": 4497.546905995453, "ENV_Online Simulation_TotalLoss_epoch0": 4710.830023318806, "ENV_Online Simulation_Right action": 0.7147612240730477, "ENV_Online Simulation_Right action_epoch0": 0.6868235568241393, "ENV_Online Simulation_Probability to choose the right action": 0.6189110024594959, "ENV_Online Simulation_Probability to choose the right action_epoch0": 0.5869017311723599, "ENV_Online Simulation_Weighted right action": 0.710618693457308, "ENV_Online Simulation_Weighted right action_epoch0": 0.680047907328634, "ENV_Online Simulation_Weighted probability to choose the right action:": 0.6189405733574321, "ENV_Online Simulation_Weighted probability to choose the right action:_epoch0": 0.5869064730465967, "_timestamp": 1714194393.9760637, "_runtime": 9466.567129611969, "_step": 74, "ENV_Train_TotalLoss": 445.499989971665, "ENV_Train_TotalLoss_epoch0": 523.1963554538722, "ENV_Train_Right action": 0.8081085065605189, "ENV_Train_Right action_epoch0": 0.7652399481193255, "ENV_Train_Probability to choose the right action": 0.7315001269243935, "ENV_Train_Probability to choose the right action_epoch0": 0.6780728461472814, "ENV_Train_Weighted right action": 0.8081085065605189, "ENV_Train_Weighted right action_epoch0": 0.7652399481193255, "ENV_Train_Weighted probability to choose the right action:": 0.7315001269243935, "ENV_Train_Weighted probability to choose the right action:_epoch0": 0.6780728461472814, "ENV_Test_TotalLoss": 132.57407987787835, "ENV_Test_TotalLoss_epoch0": 131.73346165593156, "ENV_Test_Right action": 0.751985559566787, "ENV_Test_Right action_epoch0": 0.7492779783393502, "ENV_Test_Probability to choose the right action": 0.6936022692986735, "ENV_Test_Probability to choose the right action_epoch0": 0.6757692400822319, "ENV_Test_Weighted right action": 0.751985559566787, "ENV_Test_Weighted right action_epoch0": 0.7492779783393502, "ENV_Test_Weighted probability to choose the right action:": 0.6936022692986735, "ENV_Test_Weighted probability to choose the right action:_epoch0": 0.6757692400822319, "ENV_Test_proba_accuracy": 0.6936022692986741, "ENV_Test_proba_accuracy_epoch0": 0.6757692400822319, "ENV_Test_proba_accuracy_strategy_59": 0.7208741237390255, "ENV_Test_proba_accuracy_strategy_59_epoch0": 0.7073451903174931, "ENV_Test_proba_accuracy_strategy_19": 0.681984529504908, "ENV_Test_proba_accuracy_strategy_19_epoch0": 0.6623179665585879, "ENV_Test_proba_accuracy_per_mean_strategy": 0.7014293266219667, "ENV_Test_proba_accuracy_per_mean_strategy_epoch0": 0.6848315784380405, "ENV_Test_proba_accuracy_per_mean_user": 0.7156676991909094, "ENV_Test_proba_accuracy_per_mean_user_epoch0": 0.6987219983684552, "ENV_Test_proba_accuracy_per_mean_user_and_bot": 0.7311071700307894, "ENV_Test_proba_accuracy_per_mean_user_and_bot_epoch0": 0.7153091529586474, "ENV_Test_accuracy": 0.751985559566787, "ENV_Test_accuracy_epoch0": 0.7492779783393502, "ENV_Test_accuracy_strategy_59": 0.7939577039274924, "ENV_Test_accuracy_strategy_59_epoch0": 0.7903323262839879, "ENV_Test_accuracy_strategy_19": 0.7341055341055341, "ENV_Test_accuracy_strategy_19_epoch0": 0.7317889317889318, "ENV_Test_accuracy_per_mean_strategy": 0.7640316190165133, "ENV_Test_accuracy_per_mean_strategy_epoch0": 0.7610606290364599, "ENV_Test_accuracy_per_mean_user": 0.7822199927680425, "ENV_Test_accuracy_per_mean_user_epoch0": 0.7756501344479221, "ENV_Test_accuracy_per_mean_user_and_bot": 0.8054054285630959, "ENV_Test_accuracy_per_mean_user_and_bot_epoch0": 0.7937065514128167, "ENV_Online Simulation_TotalLoss_epoch1": 4696.294726955469, "ENV_Online Simulation_Right action_epoch1": 0.6929054447942171, "ENV_Online Simulation_Probability to choose the right action_epoch1": 0.5915917561076369, "ENV_Online Simulation_Weighted right action_epoch1": 0.6849984742378891, "ENV_Online Simulation_Weighted probability to choose the right action:_epoch1": 0.5916067428246978, "ENV_Train_TotalLoss_epoch1": 497.04584066435416, "ENV_Train_Right action_epoch1": 0.7827574006368676, "ENV_Train_Probability to choose the right action_epoch1": 0.6968180011236019, "ENV_Train_Weighted right action_epoch1": 0.7827574006368676, "ENV_Train_Weighted probability to choose the right action:_epoch1": 0.6968180011236019, "ENV_Test_TotalLoss_epoch1": 136.2470548171736, "ENV_Test_Right action_epoch1": 0.7498194945848375, "ENV_Test_Probability to choose the right action_epoch1": 0.690555291650838, "ENV_Test_Weighted right action_epoch1": 0.7498194945848375, "ENV_Test_Weighted probability to choose the right action:_epoch1": 0.690555291650838, "ENV_Test_proba_accuracy_epoch1": 0.6905552916508377, "ENV_Test_proba_accuracy_strategy_59_epoch1": 0.7205687848127034, "ENV_Test_proba_accuracy_strategy_19_epoch1": 0.6777696208186915, "ENV_Test_proba_accuracy_per_mean_strategy_epoch1": 0.6991692028156975, "ENV_Test_proba_accuracy_per_mean_user_epoch1": 0.7147527060757582, "ENV_Test_proba_accuracy_per_mean_user_and_bot_epoch1": 0.7303934158946714, "ENV_Test_accuracy_epoch1": 0.7498194945848375, "ENV_Test_accuracy_strategy_59_epoch1": 0.7848942598187311, "ENV_Test_accuracy_strategy_19_epoch1": 0.7348777348777349, "ENV_Test_accuracy_per_mean_strategy_epoch1": 0.759885997348233, "ENV_Test_accuracy_per_mean_user_epoch1": 0.7766266776913298, "ENV_Test_accuracy_per_mean_user_and_bot_epoch1": 0.7952574009653117, "ENV_Online Simulation_TotalLoss_epoch2": 4682.713227704265, "ENV_Online Simulation_Right action_epoch2": 0.7008774714966085, "ENV_Online Simulation_Probability to choose the right action_epoch2": 0.5978475362636906, "ENV_Online Simulation_Weighted right action_epoch2": 0.6921519451132331, "ENV_Online Simulation_Weighted probability to choose the right action:_epoch2": 0.5978612130679428, "ENV_Train_TotalLoss_epoch2": 491.22465725253613, "ENV_Train_Right action_epoch2": 0.7855142528667866, "ENV_Train_Probability to choose the right action_epoch2": 0.7013874801108555, "ENV_Train_Weighted right action_epoch2": 0.7855142528667866, "ENV_Train_Weighted probability to choose the right action:_epoch2": 0.7013874801108555, "ENV_Test_TotalLoss_epoch2": 127.00526313026351, "ENV_Test_Right action_epoch2": 0.7543321299638989, "ENV_Test_Probability to choose the right action_epoch2": 0.6745711583850806, "ENV_Test_Weighted right action_epoch2": 0.7543321299638989, "ENV_Test_Weighted probability to choose the right action:_epoch2": 0.6745711583850806, "ENV_Test_proba_accuracy_epoch2": 0.6745711583850805, "ENV_Test_proba_accuracy_strategy_59_epoch2": 0.7029832391589653, "ENV_Test_proba_accuracy_strategy_19_epoch2": 0.6624676851081747, "ENV_Test_proba_accuracy_per_mean_strategy_epoch2": 0.68272546213357, "ENV_Test_proba_accuracy_per_mean_user_epoch2": 0.6968545469312577, "ENV_Test_proba_accuracy_per_mean_user_and_bot_epoch2": 0.7112270831136591, "ENV_Test_accuracy_epoch2": 0.7543321299638989, "ENV_Test_accuracy_strategy_59_epoch2": 0.7939577039274924, "ENV_Test_accuracy_strategy_19_epoch2": 0.7374517374517374, "ENV_Test_accuracy_per_mean_strategy_epoch2": 0.7657047206896149, "ENV_Test_accuracy_per_mean_user_epoch2": 0.7825577358984249, "ENV_Test_accuracy_per_mean_user_and_bot_epoch2": 0.805417476402357, "ENV_Online Simulation_TotalLoss_epoch3": 4540.710256968511, "ENV_Online Simulation_Right action_epoch3": 0.7058635831381733, "ENV_Online Simulation_Probability to choose the right action_epoch3": 0.6022137927191803, "ENV_Online Simulation_Weighted right action_epoch3": 0.6968503745783847, "ENV_Online Simulation_Weighted probability to choose the right action:_epoch3": 0.6022401309360741, "ENV_Train_TotalLoss_epoch3": 485.59230190639596, "ENV_Train_Right action_epoch3": 0.7878493102228511, "ENV_Train_Probability to choose the right action_epoch3": 0.7047116817615303, "ENV_Train_Weighted right action_epoch3": 0.7878493102228511, "ENV_Train_Weighted probability to choose the right action:_epoch3": 0.7047116817615303, "ENV_Test_TotalLoss_epoch3": 128.91650722129094, "ENV_Test_Right action_epoch3": 0.7577617328519856, "ENV_Test_Probability to choose the right action_epoch3": 0.6817994937757293, "ENV_Test_Weighted right action_epoch3": 0.7577617328519856, "ENV_Test_Weighted probability to choose the right action:_epoch3": 0.6817994937757293, "ENV_Test_proba_accuracy_epoch3": 0.6817994937757296, "ENV_Test_proba_accuracy_strategy_59_epoch3": 0.7141298514557791, "ENV_Test_proba_accuracy_strategy_19_epoch3": 0.6680268446224522, "ENV_Test_proba_accuracy_per_mean_strategy_epoch3": 0.6910783480391156, "ENV_Test_proba_accuracy_per_mean_user_epoch3": 0.7052913306076887, "ENV_Test_proba_accuracy_per_mean_user_and_bot_epoch3": 0.7196163465192873, "ENV_Test_accuracy_epoch3": 0.7577617328519856, "ENV_Test_accuracy_strategy_59_epoch3": 0.8030211480362538, "ENV_Test_accuracy_strategy_19_epoch3": 0.7384813384813385, "ENV_Test_accuracy_per_mean_strategy_epoch3": 0.7707512432587962, "ENV_Test_accuracy_per_mean_user_epoch3": 0.7843198831702873, "ENV_Test_accuracy_per_mean_user_and_bot_epoch3": 0.8024275594404593, "ENV_Online Simulation_TotalLoss_epoch4": 4634.52092606076, "ENV_Online Simulation_Right action_epoch4": 0.7074054908725025, "ENV_Online Simulation_Probability to choose the right action_epoch4": 0.6040938433628595, "ENV_Online Simulation_Weighted right action_epoch4": 0.6997129672213919, "ENV_Online Simulation_Weighted probability to choose the right action:_epoch4": 0.6041186560290449, "ENV_Train_TotalLoss_epoch4": 481.98625861563534, "ENV_Train_Right action_epoch4": 0.7920646150218135, "ENV_Train_Probability to choose the right action_epoch4": 0.708276375783507, "ENV_Train_Weighted right action_epoch4": 0.7920646150218135, "ENV_Train_Weighted probability to choose the right action:_epoch4": 0.708276375783507, "ENV_Test_TotalLoss_epoch4": 130.25323282744344, "ENV_Test_Right action_epoch4": 0.7545126353790613, "ENV_Test_Probability to choose the right action_epoch4": 0.6889762894826907, "ENV_Test_Weighted right action_epoch4": 0.7545126353790613, "ENV_Test_Weighted probability to choose the right action:_epoch4": 0.6889762894826907, "ENV_Test_proba_accuracy_epoch4": 0.6889762894826909, "ENV_Test_proba_accuracy_strategy_59_epoch4": 0.7184155843904894, "ENV_Test_proba_accuracy_strategy_19_epoch4": 0.6764352256287894, "ENV_Test_proba_accuracy_per_mean_strategy_epoch4": 0.6974254050096393, "ENV_Test_proba_accuracy_per_mean_user_epoch4": 0.7121519720618702, "ENV_Test_proba_accuracy_per_mean_user_and_bot_epoch4": 0.7271628541498069, "ENV_Test_accuracy_epoch4": 0.7545126353790613, "ENV_Test_accuracy_strategy_59_epoch4": 0.7915407854984894, "ENV_Test_accuracy_strategy_19_epoch4": 0.7387387387387387, "ENV_Test_accuracy_per_mean_strategy_epoch4": 0.765139762118614, "ENV_Test_accuracy_per_mean_user_epoch4": 0.7825965482943731, "ENV_Test_accuracy_per_mean_user_and_bot_epoch4": 0.8019212727699889, "ENV_Online Simulation_TotalLoss_epoch5": 4483.6375470561825, "ENV_Online Simulation_Right action_epoch5": 0.7117932148626818, "ENV_Online Simulation_Probability to choose the right action_epoch5": 0.608662501737765, "ENV_Online Simulation_Weighted right action_epoch5": 0.7043173441583979, "ENV_Online Simulation_Weighted probability to choose the right action:_epoch5": 0.6086848811110162, "ENV_Train_TotalLoss_epoch5": 479.9892055959932, "ENV_Train_Right action_epoch5": 0.7909739417521519, "ENV_Train_Probability to choose the right action_epoch5": 0.7088819398653806, "ENV_Train_Weighted right action_epoch5": 0.7909739417521519, "ENV_Train_Weighted probability to choose the right action:_epoch5": 0.7088819398653806, "ENV_Test_TotalLoss_epoch5": 130.5613044303294, "ENV_Test_Right action_epoch5": 0.7586642599277978, "ENV_Test_Probability to choose the right action_epoch5": 0.6966193585610044, "ENV_Test_Weighted right action_epoch5": 0.7586642599277978, "ENV_Test_Weighted probability to choose the right action:_epoch5": 0.6966193585610044, "ENV_Test_proba_accuracy_epoch5": 0.6966193585610048, "ENV_Test_proba_accuracy_strategy_59_epoch5": 0.7293945678752277, "ENV_Test_proba_accuracy_strategy_19_epoch5": 0.6826572037566189, "ENV_Test_proba_accuracy_per_mean_strategy_epoch5": 0.7060258858159233, "ENV_Test_proba_accuracy_per_mean_user_epoch5": 0.7211896512287249, "ENV_Test_proba_accuracy_per_mean_user_and_bot_epoch5": 0.7375010168645234, "ENV_Test_accuracy_epoch5": 0.7586642599277978, "ENV_Test_accuracy_strategy_59_epoch5": 0.7969788519637462, "ENV_Test_accuracy_strategy_19_epoch5": 0.7423423423423423, "ENV_Test_accuracy_per_mean_strategy_epoch5": 0.7696605971530442, "ENV_Test_accuracy_per_mean_user_epoch5": 0.78639669616798, "ENV_Test_accuracy_per_mean_user_and_bot_epoch5": 0.8068101595626006, "ENV_Online Simulation_TotalLoss_epoch6": 4470.654077752026, "ENV_Online Simulation_Right action_epoch6": 0.7123028856073333, "ENV_Online Simulation_Probability to choose the right action_epoch6": 0.610810322330509, "ENV_Online Simulation_Weighted right action_epoch6": 0.7054626919492064, "ENV_Online Simulation_Weighted probability to choose the right action:_epoch6": 0.6108442037353012, "ENV_Train_TotalLoss_epoch6": 474.4146292266532, "ENV_Train_Right action_epoch6": 0.7934897983252742, "ENV_Train_Probability to choose the right action_epoch6": 0.7128823634053716, "ENV_Train_Weighted right action_epoch6": 0.7934897983252742, "ENV_Train_Weighted probability to choose the right action:_epoch6": 0.7128823634053716, "ENV_Test_TotalLoss_epoch6": 128.3693224540239, "ENV_Test_Right action_epoch6": 0.7595667870036101, "ENV_Test_Probability to choose the right action_epoch6": 0.6939125009233545, "ENV_Test_Weighted right action_epoch6": 0.7595667870036101, "ENV_Test_Weighted probability to choose the right action:_epoch6": 0.6939125009233545, "ENV_Test_proba_accuracy_epoch6": 0.6939125009233543, "ENV_Test_proba_accuracy_strategy_59_epoch6": 0.7257584193237749, "ENV_Test_proba_accuracy_strategy_19_epoch6": 0.6803462216562512, "ENV_Test_proba_accuracy_per_mean_strategy_epoch6": 0.703052320490013, "ENV_Test_proba_accuracy_per_mean_user_epoch6": 0.7172783589925509, "ENV_Test_proba_accuracy_per_mean_user_and_bot_epoch6": 0.7329130902840825, "ENV_Test_accuracy_epoch6": 0.7595667870036101, "ENV_Test_accuracy_strategy_59_epoch6": 0.8036253776435045, "ENV_Test_accuracy_strategy_19_epoch6": 0.7407979407979408, "ENV_Test_accuracy_per_mean_strategy_epoch6": 0.7722116592207227, "ENV_Test_accuracy_per_mean_user_epoch6": 0.7887164362623192, "ENV_Test_accuracy_per_mean_user_and_bot_epoch6": 0.8090419511870712, "ENV_Online Simulation_TotalLoss_epoch7": 4509.401583007742, "ENV_Online Simulation_Right action_epoch7": 0.7146358482337549, "ENV_Online Simulation_Probability to choose the right action_epoch7": 0.6140507536983519, "ENV_Online Simulation_Weighted right action_epoch7": 0.7081920470290818, "ENV_Online Simulation_Weighted probability to choose the right action:_epoch7": 0.6140710432301597, "ENV_Train_TotalLoss_epoch7": 472.38599303807274, "ENV_Train_Right action_epoch7": 0.7951302912392406, "ENV_Train_Probability to choose the right action_epoch7": 0.7143000733121679, "ENV_Train_Weighted right action_epoch7": 0.7951302912392406, "ENV_Train_Weighted probability to choose the right action:_epoch7": 0.7143000733121679, "ENV_Test_TotalLoss_epoch7": 126.61865616891156, "ENV_Test_Right action_epoch7": 0.7584837545126354, "ENV_Test_Probability to choose the right action_epoch7": 0.6852631610079764, "ENV_Test_Weighted right action_epoch7": 0.7584837545126354, "ENV_Test_Weighted probability to choose the right action:_epoch7": 0.6852631610079764, "ENV_Test_proba_accuracy_epoch7": 0.6852631610079767, "ENV_Test_proba_accuracy_strategy_59_epoch7": 0.7142258967308732, "ENV_Test_proba_accuracy_strategy_19_epoch7": 0.6729251101401791, "ENV_Test_proba_accuracy_per_mean_strategy_epoch7": 0.6935755034355262, "ENV_Test_proba_accuracy_per_mean_user_epoch7": 0.7088365912435515, "ENV_Test_proba_accuracy_per_mean_user_and_bot_epoch7": 0.7239603133089021, "ENV_Test_accuracy_epoch7": 0.7584837545126354, "ENV_Test_accuracy_strategy_59_epoch7": 0.7987915407854985, "ENV_Test_accuracy_strategy_19_epoch7": 0.7413127413127413, "ENV_Test_accuracy_per_mean_strategy_epoch7": 0.7700521410491199, "ENV_Test_accuracy_per_mean_user_epoch7": 0.7901396469462683, "ENV_Test_accuracy_per_mean_user_and_bot_epoch7": 0.8116494213085346, "ENV_Online Simulation_TotalLoss_epoch8": 4539.157844734423, "ENV_Online Simulation_Right action_epoch8": 0.714590017052516, "ENV_Online Simulation_Probability to choose the right action_epoch8": 0.6136862840519739, "ENV_Online Simulation_Weighted right action_epoch8": 0.7081578185962799, "ENV_Online Simulation_Weighted probability to choose the right action:_epoch8": 0.6137088315474432, "ENV_Train_TotalLoss_epoch8": 470.6659199228799, "ENV_Train_Right action_epoch8": 0.7958780516570351, "ENV_Train_Probability to choose the right action_epoch8": 0.7155873096213915, "ENV_Train_Weighted right action_epoch8": 0.7958780516570351, "ENV_Train_Weighted probability to choose the right action:_epoch8": 0.7155873096213915, "ENV_Test_TotalLoss_epoch8": 127.82369751097383, "ENV_Test_Right action_epoch8": 0.7583032490974729, "ENV_Test_Probability to choose the right action_epoch8": 0.6907404989260084, "ENV_Test_Weighted right action_epoch8": 0.7583032490974729, "ENV_Test_Weighted probability to choose the right action:_epoch8": 0.6907404989260084, "ENV_Test_proba_accuracy_epoch8": 0.6907404989260081, "ENV_Test_proba_accuracy_strategy_59_epoch8": 0.7223548525245344, "ENV_Test_proba_accuracy_strategy_19_epoch8": 0.6772728656684635, "ENV_Test_proba_accuracy_per_mean_strategy_epoch8": 0.6998138590964988, "ENV_Test_proba_accuracy_per_mean_user_epoch8": 0.7145722196353189, "ENV_Test_proba_accuracy_per_mean_user_and_bot_epoch8": 0.7301761116830336, "ENV_Test_accuracy_epoch8": 0.7583032490974729, "ENV_Test_accuracy_strategy_59_epoch8": 0.8036253776435045, "ENV_Test_accuracy_strategy_19_epoch8": 0.738996138996139, "ENV_Test_accuracy_per_mean_strategy_epoch8": 0.7713107583198218, "ENV_Test_accuracy_per_mean_user_epoch8": 0.7847948101291723, "ENV_Test_accuracy_per_mean_user_and_bot_epoch8": 0.8061449676574888, "ENV_Online Simulation_TotalLoss_epoch9": 4470.637631820182, "ENV_Online Simulation_Right action_epoch9": 0.714579724611726, "ENV_Online Simulation_Probability to choose the right action_epoch9": 0.6144985254585923, "ENV_Online Simulation_Weighted right action_epoch9": 0.7088617216765473, "ENV_Online Simulation_Weighted probability to choose the right action:_epoch9": 0.6145210048287656, "ENV_Train_TotalLoss_epoch9": 466.5066282582438, "ENV_Train_Right action_epoch9": 0.7983547588158981, "ENV_Train_Probability to choose the right action_epoch9": 0.7181872547840317, "ENV_Train_Weighted right action_epoch9": 0.7983547588158981, "ENV_Train_Weighted probability to choose the right action:_epoch9": 0.7181872547840317, "ENV_Test_TotalLoss_epoch9": 127.90009182514406, "ENV_Test_Right action_epoch9": 0.7595667870036101, "ENV_Test_Probability to choose the right action_epoch9": 0.6923624421091295, "ENV_Test_Weighted right action_epoch9": 0.7595667870036101, "ENV_Test_Weighted probability to choose the right action:_epoch9": 0.6923624421091295, "ENV_Test_proba_accuracy_epoch9": 0.6923624421091293, "ENV_Test_proba_accuracy_strategy_59_epoch9": 0.7235915592882861, "ENV_Test_proba_accuracy_strategy_19_epoch9": 0.6790589185746364, "ENV_Test_proba_accuracy_per_mean_strategy_epoch9": 0.7013252389314613, "ENV_Test_proba_accuracy_per_mean_user_epoch9": 0.7151369254716562, "ENV_Test_proba_accuracy_per_mean_user_and_bot_epoch9": 0.7310271536701516, "ENV_Test_accuracy_epoch9": 0.7595667870036101, "ENV_Test_accuracy_strategy_59_epoch9": 0.8042296072507553, "ENV_Test_accuracy_strategy_19_epoch9": 0.7405405405405405, "ENV_Test_accuracy_per_mean_strategy_epoch9": 0.7723850738956479, "ENV_Test_accuracy_per_mean_user_epoch9": 0.7887993247564808, "ENV_Test_accuracy_per_mean_user_and_bot_epoch9": 0.8107795609368641, "ENV_Online Simulation_TotalLoss_epoch10": 4467.34664072634, "ENV_Online Simulation_Right action_epoch10": 0.7136648680180837, "ENV_Online Simulation_Probability to choose the right action_epoch10": 0.6137126116816481, "ENV_Online Simulation_Weighted right action_epoch10": 0.7074042171329816, "ENV_Online Simulation_Weighted probability to choose the right action:_epoch10": 0.6137336274524375, "ENV_Train_TotalLoss_epoch10": 465.8408234657707, "ENV_Train_Right action_epoch10": 0.8001709704044334, "ENV_Train_Probability to choose the right action_epoch10": 0.7189376161455628, "ENV_Train_Weighted right action_epoch10": 0.8001709704044334, "ENV_Train_Weighted probability to choose the right action:_epoch10": 0.7189376161455628, "ENV_Test_TotalLoss_epoch10": 130.24783126429335, "ENV_Test_Right action_epoch10": 0.7601083032490975, "ENV_Test_Probability to choose the right action_epoch10": 0.6996201880140636, "ENV_Test_Weighted right action_epoch10": 0.7601083032490975, "ENV_Test_Weighted probability to choose the right action:_epoch10": 0.6996201880140636, "ENV_Test_proba_accuracy_epoch10": 0.6996201880140632, "ENV_Test_proba_accuracy_strategy_59_epoch10": 0.7277873674051915, "ENV_Test_proba_accuracy_strategy_19_epoch10": 0.6876210420958349, "ENV_Test_proba_accuracy_per_mean_strategy_epoch10": 0.7077042047505131, "ENV_Test_proba_accuracy_per_mean_user_epoch10": 0.7212707085811347, "ENV_Test_proba_accuracy_per_mean_user_and_bot_epoch10": 0.7363776175971545, "ENV_Test_accuracy_epoch10": 0.7601083032490975, "ENV_Test_accuracy_strategy_59_epoch10": 0.7969788519637462, "ENV_Test_accuracy_strategy_19_epoch10": 0.7444015444015444, "ENV_Test_accuracy_per_mean_strategy_epoch10": 0.7706901981826453, "ENV_Test_accuracy_per_mean_user_epoch10": 0.7882825282191055, "ENV_Test_accuracy_per_mean_user_and_bot_epoch10": 0.810625018091863, "ENV_Online Simulation_TotalLoss_epoch11": 4525.57814624836, "ENV_Online Simulation_Right action_epoch11": 0.7152973271033461, "ENV_Online Simulation_Probability to choose the right action_epoch11": 0.6158344870777273, "ENV_Online Simulation_Weighted right action_epoch11": 0.7098140348049792, "ENV_Online Simulation_Weighted probability to choose the right action:_epoch11": 0.6158593773287218, "ENV_Train_TotalLoss_epoch11": 463.56006208006244, "ENV_Train_Right action_epoch11": 0.7998879584856705, "ENV_Train_Probability to choose the right action_epoch11": 0.7199680460873304, "ENV_Train_Weighted right action_epoch11": 0.7998879584856705, "ENV_Train_Weighted probability to choose the right action:_epoch11": 0.7199680460873304, "ENV_Test_TotalLoss_epoch11": 130.4008459998057, "ENV_Test_Right action_epoch11": 0.7595667870036101, "ENV_Test_Probability to choose the right action_epoch11": 0.6982189297244915, "ENV_Test_Weighted right action_epoch11": 0.7595667870036101, "ENV_Test_Weighted probability to choose the right action:_epoch11": 0.6982189297244915, "ENV_Test_proba_accuracy_epoch11": 0.6982189297244917, "ENV_Test_proba_accuracy_strategy_59_epoch11": 0.7278420468758192, "ENV_Test_proba_accuracy_strategy_19_epoch11": 0.6855995580680061, "ENV_Test_proba_accuracy_per_mean_strategy_epoch11": 0.7067208024719127, "ENV_Test_proba_accuracy_per_mean_user_epoch11": 0.7223703884243634, "ENV_Test_proba_accuracy_per_mean_user_and_bot_epoch11": 0.7376514576135232, "ENV_Test_accuracy_epoch11": 0.7595667870036101, "ENV_Test_accuracy_strategy_59_epoch11": 0.8, "ENV_Test_accuracy_strategy_19_epoch11": 0.7423423423423423, "ENV_Test_accuracy_per_mean_strategy_epoch11": 0.7711711711711712, "ENV_Test_accuracy_per_mean_user_epoch11": 0.7914694781052882, "ENV_Test_accuracy_per_mean_user_and_bot_epoch11": 0.8130209752105613, "ENV_Online Simulation_TotalLoss_epoch12": 4471.410047305858, "ENV_Online Simulation_Right action_epoch12": 0.7159009363787521, "ENV_Online Simulation_Probability to choose the right action_epoch12": 0.6174421967537653, "ENV_Online Simulation_Weighted right action_epoch12": 0.7103042931088057, "ENV_Online Simulation_Weighted probability to choose the right action:_epoch12": 0.6174622019174332, "ENV_Train_TotalLoss_epoch12": 463.06008826971015, "ENV_Train_Right action_epoch12": 0.7999174430947046, "ENV_Train_Probability to choose the right action_epoch12": 0.7214373416929883, "ENV_Train_Weighted right action_epoch12": 0.7999174430947046, "ENV_Train_Weighted probability to choose the right action:_epoch12": 0.7214373416929883, "ENV_Test_TotalLoss_epoch12": 127.65498954575209, "ENV_Test_Right action_epoch12": 0.7581227436823105, "ENV_Test_Probability to choose the right action_epoch12": 0.6925418710282778, "ENV_Test_Weighted right action_epoch12": 0.7581227436823105, "ENV_Test_Weighted probability to choose the right action:_epoch12": 0.6925418710282778, "ENV_Test_proba_accuracy_epoch12": 0.6925418710282782, "ENV_Test_proba_accuracy_strategy_59_epoch12": 0.7200833020795137, "ENV_Test_proba_accuracy_strategy_19_epoch12": 0.6808092922921666, "ENV_Test_proba_accuracy_per_mean_strategy_epoch12": 0.70044629718584, "ENV_Test_proba_accuracy_per_mean_user_epoch12": 0.7144313253503741, "ENV_Test_proba_accuracy_per_mean_user_and_bot_epoch12": 0.7296280111667184, "ENV_Test_accuracy_epoch12": 0.7581227436823105, "ENV_Test_accuracy_strategy_59_epoch12": 0.8054380664652568, "ENV_Test_accuracy_strategy_19_epoch12": 0.737966537966538, "ENV_Test_accuracy_per_mean_strategy_epoch12": 0.7717023022158974, "ENV_Test_accuracy_per_mean_user_epoch12": 0.7871407509397673, "ENV_Test_accuracy_per_mean_user_and_bot_epoch12": 0.8130511784977602, "ENV_Online Simulation_TotalLoss_epoch13": 4376.233374124386, "ENV_Online Simulation_Right action_epoch13": 0.7176993518463459, "ENV_Online Simulation_Probability to choose the right action_epoch13": 0.6187121764429754, "ENV_Online Simulation_Weighted right action_epoch13": 0.7116536300963696, "ENV_Online Simulation_Weighted probability to choose the right action:_epoch13": 0.6187347793691855, "ENV_Train_TotalLoss_epoch13": 458.8995993198821, "ENV_Train_Right action_epoch13": 0.8013563320064868, "ENV_Train_Probability to choose the right action_epoch13": 0.7237664987319269, "ENV_Train_Weighted right action_epoch13": 0.8013563320064868, "ENV_Train_Weighted probability to choose the right action:_epoch13": 0.7237664987319269, "ENV_Test_TotalLoss_epoch13": 126.15668740889392, "ENV_Test_Right action_epoch13": 0.7568592057761733, "ENV_Test_Probability to choose the right action_epoch13": 0.6906053667151643, "ENV_Test_Weighted right action_epoch13": 0.7568592057761733, "ENV_Test_Weighted probability to choose the right action:_epoch13": 0.6906053667151643, "ENV_Test_proba_accuracy_epoch13": 0.6906053667151641, "ENV_Test_proba_accuracy_strategy_59_epoch13": 0.7181924163772866, "ENV_Test_proba_accuracy_strategy_19_epoch13": 0.6788533545682369, "ENV_Test_proba_accuracy_per_mean_strategy_epoch13": 0.6985228854727616, "ENV_Test_proba_accuracy_per_mean_user_epoch13": 0.7121712401573105, "ENV_Test_proba_accuracy_per_mean_user_and_bot_epoch13": 0.7261995540128167, "ENV_Test_accuracy_epoch13": 0.7568592057761733, "ENV_Test_accuracy_strategy_59_epoch13": 0.7987915407854985, "ENV_Test_accuracy_strategy_19_epoch13": 0.738996138996139, "ENV_Test_accuracy_per_mean_strategy_epoch13": 0.7688938398908187, "ENV_Test_accuracy_per_mean_user_epoch13": 0.7882121773442056, "ENV_Test_accuracy_per_mean_user_and_bot_epoch13": 0.8123246673769325, "ENV_Online Simulation_TotalLoss_epoch14": 4458.341987742327, "ENV_Online Simulation_Right action_epoch14": 0.7162059573481687, "ENV_Online Simulation_Probability to choose the right action_epoch14": 0.617462527510207, "ENV_Online Simulation_Weighted right action_epoch14": 0.709406166599061, "ENV_Online Simulation_Weighted probability to choose the right action:_epoch14": 0.6174931086367229, "ENV_Train_TotalLoss_epoch14": 459.09829307816966, "ENV_Train_Right action_epoch14": 0.8002948547840188, "ENV_Train_Probability to choose the right action_epoch14": 0.7235868108137999, "ENV_Train_Weighted right action_epoch14": 0.8002948547840188, "ENV_Train_Weighted probability to choose the right action:_epoch14": 0.7235868108137999, "ENV_Test_TotalLoss_epoch14": 126.34765932339543, "ENV_Test_Right action_epoch14": 0.7575812274368231, "ENV_Test_Probability to choose the right action_epoch14": 0.6878142445971528, "ENV_Test_Weighted right action_epoch14": 0.7575812274368231, "ENV_Test_Weighted probability to choose the right action:_epoch14": 0.6878142445971528, "ENV_Test_proba_accuracy_epoch14": 0.6878142445971527, "ENV_Test_proba_accuracy_strategy_59_epoch14": 0.7125390445332661, "ENV_Test_proba_accuracy_strategy_19_epoch14": 0.677281543466067, "ENV_Test_proba_accuracy_per_mean_strategy_epoch14": 0.6949102939996666, "ENV_Test_proba_accuracy_per_mean_user_epoch14": 0.7078648617048422, "ENV_Test_proba_accuracy_per_mean_user_and_bot_epoch14": 0.7202920027401293, "ENV_Test_accuracy_epoch14": 0.7575812274368231, "ENV_Test_accuracy_strategy_59_epoch14": 0.7945619335347432, "ENV_Test_accuracy_strategy_19_epoch14": 0.7418275418275418, "ENV_Test_accuracy_per_mean_strategy_epoch14": 0.7681947376811425, "ENV_Test_accuracy_per_mean_user_epoch14": 0.786188254140089, "ENV_Test_accuracy_per_mean_user_and_bot_epoch14": 0.8100326181135683, "ENV_Online Simulation_TotalLoss_epoch15": 4534.185734319265, "ENV_Online Simulation_Right action_epoch15": 0.7154454932657994, "ENV_Online Simulation_Probability to choose the right action_epoch15": 0.6174070695677978, "ENV_Online Simulation_Weighted right action_epoch15": 0.7098669286363801, "ENV_Online Simulation_Weighted probability to choose the right action:_epoch15": 0.6174428916764553, "ENV_Train_TotalLoss_epoch15": 458.3384501437969, "ENV_Train_Right action_epoch15": 0.803219719306522, "ENV_Train_Probability to choose the right action_epoch15": 0.7237029228498807, "ENV_Train_Weighted right action_epoch15": 0.803219719306522, "ENV_Train_Weighted probability to choose the right action:_epoch15": 0.7237029228498807, "ENV_Test_TotalLoss_epoch15": 128.82930487720097, "ENV_Test_Right action_epoch15": 0.7583032490974729, "ENV_Test_Probability to choose the right action_epoch15": 0.6958050139210421, "ENV_Test_Weighted right action_epoch15": 0.7583032490974729, "ENV_Test_Weighted probability to choose the right action:_epoch15": 0.6958050139210421, "ENV_Test_proba_accuracy_epoch15": 0.6958050139210428, "ENV_Test_proba_accuracy_strategy_59_epoch15": 0.7237465321423241, "ENV_Test_proba_accuracy_strategy_19_epoch15": 0.6839019990803168, "ENV_Test_proba_accuracy_per_mean_strategy_epoch15": 0.7038242656113205, "ENV_Test_proba_accuracy_per_mean_user_epoch15": 0.7181576079964517, "ENV_Test_proba_accuracy_per_mean_user_and_bot_epoch15": 0.7324724663406733, "ENV_Test_accuracy_epoch15": 0.7583032490974729, "ENV_Test_accuracy_strategy_59_epoch15": 0.7993957703927492, "ENV_Test_accuracy_strategy_19_epoch15": 0.7407979407979408, "ENV_Test_accuracy_per_mean_strategy_epoch15": 0.770096855595345, "ENV_Test_accuracy_per_mean_user_epoch15": 0.7876223622292164, "ENV_Test_accuracy_per_mean_user_and_bot_epoch15": 0.8106382813261187, "ENV_Online Simulation_TotalLoss_epoch16": 4374.126652766203, "ENV_Online Simulation_Right action_epoch16": 0.7198385067727685, "ENV_Online Simulation_Probability to choose the right action_epoch16": 0.6209810562625336, "ENV_Online Simulation_Weighted right action_epoch16": 0.7134741115182538, "ENV_Online Simulation_Weighted probability to choose the right action:_epoch16": 0.6210106093162161, "ENV_Train_TotalLoss_epoch16": 457.7749308568303, "ENV_Train_Right action_epoch16": 0.8031187359981135, "ENV_Train_Probability to choose the right action_epoch16": 0.7254388156852152, "ENV_Train_Weighted right action_epoch16": 0.8031187359981135, "ENV_Train_Weighted probability to choose the right action:_epoch16": 0.7254388156852152, "ENV_Test_TotalLoss_epoch16": 127.78616090627168, "ENV_Test_Right action_epoch16": 0.7564981949458484, "ENV_Test_Probability to choose the right action_epoch16": 0.6919927908976664, "ENV_Test_Weighted right action_epoch16": 0.7564981949458484, "ENV_Test_Weighted probability to choose the right action:_epoch16": 0.6919927908976664, "ENV_Test_proba_accuracy_epoch16": 0.6919927908976669, "ENV_Test_proba_accuracy_strategy_59_epoch16": 0.7182523802924495, "ENV_Test_proba_accuracy_strategy_19_epoch16": 0.6808062734077401, "ENV_Test_proba_accuracy_per_mean_strategy_epoch16": 0.6995293268500948, "ENV_Test_proba_accuracy_per_mean_user_epoch16": 0.7129667816996376, "ENV_Test_proba_accuracy_per_mean_user_and_bot_epoch16": 0.7285846800115091, "ENV_Test_accuracy_epoch16": 0.7564981949458484, "ENV_Test_accuracy_strategy_59_epoch16": 0.7945619335347432, "ENV_Test_accuracy_strategy_19_epoch16": 0.7402831402831402, "ENV_Test_accuracy_per_mean_strategy_epoch16": 0.7674225369089418, "ENV_Test_accuracy_per_mean_user_epoch16": 0.7889696933279134, "ENV_Test_accuracy_per_mean_user_and_bot_epoch16": 0.8134186749880905, "ENV_Online Simulation_TotalLoss_epoch17": 4457.828822832502, "ENV_Online Simulation_Right action_epoch17": 0.716339699074074, "ENV_Online Simulation_Probability to choose the right action_epoch17": 0.6194078426451389, "ENV_Online Simulation_Weighted right action_epoch17": 0.7108786300452479, "ENV_Online Simulation_Weighted probability to choose the right action:_epoch17": 0.6194343363359126, "ENV_Train_TotalLoss_epoch17": 453.6583221189156, "ENV_Train_Right action_epoch17": 0.8040747729685105, "ENV_Train_Probability to choose the right action_epoch17": 0.7267861350707223, "ENV_Train_Weighted right action_epoch17": 0.8040747729685105, "ENV_Train_Weighted probability to choose the right action:_epoch17": 0.7267861350707223, "ENV_Test_TotalLoss_epoch17": 128.69992240123005, "ENV_Test_Right action_epoch17": 0.7577617328519856, "ENV_Test_Probability to choose the right action_epoch17": 0.6925581835034734, "ENV_Test_Weighted right action_epoch17": 0.7577617328519856, "ENV_Test_Weighted probability to choose the right action:_epoch17": 0.6925581835034734, "ENV_Test_proba_accuracy_epoch17": 0.6925581835034735, "ENV_Test_proba_accuracy_strategy_59_epoch17": 0.7204677374525355, "ENV_Test_proba_accuracy_strategy_19_epoch17": 0.6806687853604371, "ENV_Test_proba_accuracy_per_mean_strategy_epoch17": 0.7005682614064861, "ENV_Test_proba_accuracy_per_mean_user_epoch17": 0.7148485472641429, "ENV_Test_proba_accuracy_per_mean_user_and_bot_epoch17": 0.7303657415275314, "ENV_Test_accuracy_epoch17": 0.7577617328519856, "ENV_Test_accuracy_strategy_59_epoch17": 0.8060422960725075, "ENV_Test_accuracy_strategy_19_epoch17": 0.7371943371943372, "ENV_Test_accuracy_per_mean_strategy_epoch17": 0.7716183166334224, "ENV_Test_accuracy_per_mean_user_epoch17": 0.7888378672878008, "ENV_Test_accuracy_per_mean_user_and_bot_epoch17": 0.8142302688444704, "ENV_Online Simulation_TotalLoss_epoch18": 4382.772356330318, "ENV_Online Simulation_Right action_epoch18": 0.7175840707964601, "ENV_Online Simulation_Probability to choose the right action_epoch18": 0.6200785334393322, "ENV_Online Simulation_Weighted right action_epoch18": 0.7121814917635472, "ENV_Online Simulation_Weighted probability to choose the right action:_epoch18": 0.6201106105822856, "ENV_Train_TotalLoss_epoch18": 452.1386992229297, "ENV_Train_Right action_epoch18": 0.8056612118531623, "ENV_Train_Probability to choose the right action_epoch18": 0.7288000809076863, "ENV_Train_Weighted right action_epoch18": 0.8056612118531623, "ENV_Train_Weighted probability to choose the right action:_epoch18": 0.7288000809076863, "ENV_Test_TotalLoss_epoch18": 128.7489579741117, "ENV_Test_Right action_epoch18": 0.7509025270758123, "ENV_Test_Probability to choose the right action_epoch18": 0.6884717588141565, "ENV_Test_Weighted right action_epoch18": 0.7509025270758123, "ENV_Test_Weighted probability to choose the right action:_epoch18": 0.6884717588141565, "ENV_Test_proba_accuracy_epoch18": 0.6884717588141567, "ENV_Test_proba_accuracy_strategy_59_epoch18": 0.7130657103633188, "ENV_Test_proba_accuracy_strategy_19_epoch18": 0.6779947987591082, "ENV_Test_proba_accuracy_per_mean_strategy_epoch18": 0.6955302545612134, "ENV_Test_proba_accuracy_per_mean_user_epoch18": 0.7082976369092937, "ENV_Test_proba_accuracy_per_mean_user_and_bot_epoch18": 0.7221139853963162, "ENV_Test_accuracy_epoch18": 0.7509025270758123, "ENV_Test_accuracy_strategy_59_epoch18": 0.7945619335347432, "ENV_Test_accuracy_strategy_19_epoch18": 0.7323037323037324, "ENV_Test_accuracy_per_mean_strategy_epoch18": 0.7634328329192378, "ENV_Test_accuracy_per_mean_user_epoch18": 0.7794206641399695, "ENV_Test_accuracy_per_mean_user_and_bot_epoch18": 0.8012309679793936, "ENV_Online Simulation_TotalLoss_epoch19": 4493.10057731736, "ENV_Online Simulation_Right action_epoch19": 0.71524467472654, "ENV_Online Simulation_Probability to choose the right action_epoch19": 0.6187318809323721, "ENV_Online Simulation_Weighted right action_epoch19": 0.7100368080850153, "ENV_Online Simulation_Weighted probability to choose the right action:_epoch19": 0.6187625001636423, "ENV_Train_TotalLoss_epoch19": 448.57397077625666, "ENV_Train_Right action_epoch19": 0.8073475645712938, "ENV_Train_Probability to choose the right action_epoch19": 0.7301715135302322, "ENV_Train_Weighted right action_epoch19": 0.8073475645712938, "ENV_Train_Weighted probability to choose the right action:_epoch19": 0.7301715135302322, "ENV_Test_TotalLoss_epoch19": 131.2457203186432, "ENV_Test_Right action_epoch19": 0.7563176895306859, "ENV_Test_Probability to choose the right action_epoch19": 0.694086646349427, "ENV_Test_Weighted right action_epoch19": 0.7563176895306859, "ENV_Test_Weighted probability to choose the right action:_epoch19": 0.694086646349427, "ENV_Test_proba_accuracy_epoch19": 0.6940866463494263, "ENV_Test_proba_accuracy_strategy_59_epoch19": 0.7240982367363713, "ENV_Test_proba_accuracy_strategy_19_epoch19": 0.6813017860944987, "ENV_Test_proba_accuracy_per_mean_strategy_epoch19": 0.7027000114154349, "ENV_Test_proba_accuracy_per_mean_user_epoch19": 0.7159953641731934, "ENV_Test_proba_accuracy_per_mean_user_and_bot_epoch19": 0.7318011245213215, "ENV_Test_accuracy_epoch19": 0.7563176895306859, "ENV_Test_accuracy_strategy_59_epoch19": 0.8, "ENV_Test_accuracy_strategy_19_epoch19": 0.7377091377091377, "ENV_Test_accuracy_per_mean_strategy_epoch19": 0.7688545688545689, "ENV_Test_accuracy_per_mean_user_epoch19": 0.7854409193188552, "ENV_Test_accuracy_per_mean_user_and_bot_epoch19": 0.8102517489287008, "ENV_Online Simulation_TotalLoss_epoch20": 4551.208864693648, "ENV_Online Simulation_Right action_epoch20": 0.7139498792964709, "ENV_Online Simulation_Probability to choose the right action_epoch20": 0.617111222714467, "ENV_Online Simulation_Weighted right action_epoch20": 0.7092099165518341, "ENV_Online Simulation_Weighted probability to choose the right action:_epoch20": 0.6171500119609563, "ENV_Train_TotalLoss_epoch20": 448.85816106657103, "ENV_Train_Right action_epoch20": 0.8079667413610095, "ENV_Train_Probability to choose the right action_epoch20": 0.7305930006328193, "ENV_Train_Weighted right action_epoch20": 0.8079667413610095, "ENV_Train_Weighted probability to choose the right action:_epoch20": 0.7305930006328193, "ENV_Test_TotalLoss_epoch20": 132.309277227243, "ENV_Test_Right action_epoch20": 0.7532490974729242, "ENV_Test_Probability to choose the right action_epoch20": 0.6916655596652754, "ENV_Test_Weighted right action_epoch20": 0.7532490974729242, "ENV_Test_Weighted probability to choose the right action:_epoch20": 0.6916655596652754, "ENV_Test_proba_accuracy_epoch20": 0.6916655596652754, "ENV_Test_proba_accuracy_strategy_59_epoch20": 0.7175075234470601, "ENV_Test_proba_accuracy_strategy_19_epoch20": 0.6806569496115163, "ENV_Test_proba_accuracy_per_mean_strategy_epoch20": 0.6990822365292881, "ENV_Test_proba_accuracy_per_mean_user_epoch20": 0.7123565813256293, "ENV_Test_proba_accuracy_per_mean_user_and_bot_epoch20": 0.7270061651065043, "ENV_Test_accuracy_epoch20": 0.7532490974729242, "ENV_Test_accuracy_strategy_59_epoch20": 0.7963746223564955, "ENV_Test_accuracy_strategy_19_epoch20": 0.7348777348777349, "ENV_Test_accuracy_per_mean_strategy_epoch20": 0.7656261786171152, "ENV_Test_accuracy_per_mean_user_epoch20": 0.7816906795682906, "ENV_Test_accuracy_per_mean_user_and_bot_epoch20": 0.8052505160212944, "ENV_Online Simulation_TotalLoss_epoch21": 4365.216052852482, "ENV_Online Simulation_Right action_epoch21": 0.7219901900314272, "ENV_Online Simulation_Probability to choose the right action_epoch21": 0.6249420661830672, "ENV_Online Simulation_Weighted right action_epoch21": 0.7170508069554483, "ENV_Online Simulation_Weighted probability to choose the right action:_epoch21": 0.6249754234859848, "ENV_Train_TotalLoss_epoch21": 448.2618547173394, "ENV_Train_Right action_epoch21": 0.8065809647364076, "ENV_Train_Probability to choose the right action_epoch21": 0.7302851311307896, "ENV_Train_Weighted right action_epoch21": 0.8065809647364076, "ENV_Train_Weighted probability to choose the right action:_epoch21": 0.7302851311307896, "ENV_Test_TotalLoss_epoch21": 130.0905714489667, "ENV_Test_Right action_epoch21": 0.7561371841155234, "ENV_Test_Probability to choose the right action_epoch21": 0.6859940603526256, "ENV_Test_Weighted right action_epoch21": 0.7561371841155234, "ENV_Test_Weighted probability to choose the right action:_epoch21": 0.6859940603526256, "ENV_Test_proba_accuracy_epoch21": 0.685994060352625, "ENV_Test_proba_accuracy_strategy_59_epoch21": 0.712245153993152, "ENV_Test_proba_accuracy_strategy_19_epoch21": 0.6748111620321432, "ENV_Test_proba_accuracy_per_mean_strategy_epoch21": 0.6935281580126476, "ENV_Test_proba_accuracy_per_mean_user_epoch21": 0.7056444802623959, "ENV_Test_proba_accuracy_per_mean_user_and_bot_epoch21": 0.7196832753233979, "ENV_Test_accuracy_epoch21": 0.7561371841155234, "ENV_Test_accuracy_strategy_59_epoch21": 0.7993957703927492, "ENV_Test_accuracy_strategy_19_epoch21": 0.7377091377091377, "ENV_Test_accuracy_per_mean_strategy_epoch21": 0.7685524540509434, "ENV_Test_accuracy_per_mean_user_epoch21": 0.7868182870678405, "ENV_Test_accuracy_per_mean_user_and_bot_epoch21": 0.8115956255107432, "ENV_Online Simulation_TotalLoss_epoch22": 4339.028143083081, "ENV_Online Simulation_Right action_epoch22": 0.7202285243101569, "ENV_Online Simulation_Probability to choose the right action_epoch22": 0.6231890447151921, "ENV_Online Simulation_Weighted right action_epoch22": 0.7149301379316464, "ENV_Online Simulation_Weighted probability to choose the right action:_epoch22": 0.6232293239842787, "ENV_Train_TotalLoss_epoch22": 445.42721673877327, "ENV_Train_Right action_epoch22": 0.8079667413610095, "ENV_Train_Probability to choose the right action_epoch22": 0.7323106638935282, "ENV_Train_Weighted right action_epoch22": 0.8079667413610095, "ENV_Train_Weighted probability to choose the right action:_epoch22": 0.7323106638935282, "ENV_Test_TotalLoss_epoch22": 129.36806820818427, "ENV_Test_Right action_epoch22": 0.7541516245487364, "ENV_Test_Probability to choose the right action_epoch22": 0.6907410428811034, "ENV_Test_Weighted right action_epoch22": 0.7541516245487364, "ENV_Test_Weighted probability to choose the right action:_epoch22": 0.6907410428811034, "ENV_Test_proba_accuracy_epoch22": 0.6907410428811038, "ENV_Test_proba_accuracy_strategy_59_epoch22": 0.7179188709405201, "ENV_Test_proba_accuracy_strategy_19_epoch22": 0.679163358083592, "ENV_Test_proba_accuracy_per_mean_strategy_epoch22": 0.698541114512056, "ENV_Test_proba_accuracy_per_mean_user_epoch22": 0.7130055731224014, "ENV_Test_proba_accuracy_per_mean_user_and_bot_epoch22": 0.7279434563727862, "ENV_Test_accuracy_epoch22": 0.7541516245487364, "ENV_Test_accuracy_strategy_59_epoch22": 0.7957703927492447, "ENV_Test_accuracy_strategy_19_epoch22": 0.7364221364221364, "ENV_Test_accuracy_per_mean_strategy_epoch22": 0.7660962645856906, "ENV_Test_accuracy_per_mean_user_epoch22": 0.7862407115088466, "ENV_Test_accuracy_per_mean_user_and_bot_epoch22": 0.8102224883561558, "ENV_Online Simulation_TotalLoss_epoch23": 4472.411126116624, "ENV_Online Simulation_Right action_epoch23": 0.7144609632853346, "ENV_Online Simulation_Probability to choose the right action_epoch23": 0.6189475590521032, "ENV_Online Simulation_Weighted right action_epoch23": 0.7101694952691465, "ENV_Online Simulation_Weighted probability to choose the right action:_epoch23": 0.6189729680356181, "ENV_Train_TotalLoss_epoch23": 446.67450576125, "ENV_Train_Right action_epoch23": 0.8071411723080552, "ENV_Train_Probability to choose the right action_epoch23": 0.7316479764080407, "ENV_Train_Weighted right action_epoch23": 0.8071411723080552, "ENV_Train_Weighted probability to choose the right action:_epoch23": 0.7316479764080407, "ENV_Test_TotalLoss_epoch23": 133.6425745391079, "ENV_Test_Right action_epoch23": 0.7530685920577618, "ENV_Test_Probability to choose the right action_epoch23": 0.6987743590755668, "ENV_Test_Weighted right action_epoch23": 0.7530685920577618, "ENV_Test_Weighted probability to choose the right action:_epoch23": 0.6987743590755668, "ENV_Test_proba_accuracy_epoch23": 0.6987743590755665, "ENV_Test_proba_accuracy_strategy_59_epoch23": 0.7287594285814725, "ENV_Test_proba_accuracy_strategy_19_epoch23": 0.6860007966476968, "ENV_Test_proba_accuracy_per_mean_strategy_epoch23": 0.7073801126145847, "ENV_Test_proba_accuracy_per_mean_user_epoch23": 0.7221144711760407, "ENV_Test_proba_accuracy_per_mean_user_and_bot_epoch23": 0.7392648118368806, "ENV_Test_accuracy_epoch23": 0.7530685920577618, "ENV_Test_accuracy_strategy_59_epoch23": 0.7981873111782477, "ENV_Test_accuracy_strategy_19_epoch23": 0.7338481338481339, "ENV_Test_accuracy_per_mean_strategy_epoch23": 0.7660177225131908, "ENV_Test_accuracy_per_mean_user_epoch23": 0.7837313172796583, "ENV_Test_accuracy_per_mean_user_and_bot_epoch23": 0.8071519260617976, "ENV_Online Simulation_TotalLoss_epoch24": 4497.546905995453, "ENV_Online Simulation_Right action_epoch24": 0.7147612240730477, "ENV_Online Simulation_Probability to choose the right action_epoch24": 0.6189110024594959, "ENV_Online Simulation_Weighted right action_epoch24": 0.710618693457308, "ENV_Online Simulation_Weighted probability to choose the right action:_epoch24": 0.6189405733574321, "ENV_Train_TotalLoss_epoch24": 445.499989971665, "ENV_Train_Right action_epoch24": 0.8081085065605189, "ENV_Train_Probability to choose the right action_epoch24": 0.7315001269243935, "ENV_Train_Weighted right action_epoch24": 0.8081085065605189, "ENV_Train_Weighted probability to choose the right action:_epoch24": 0.7315001269243935, "ENV_Test_TotalLoss_epoch24": 132.57407987787835, "ENV_Test_Right action_epoch24": 0.751985559566787, "ENV_Test_Probability to choose the right action_epoch24": 0.6936022692986735, "ENV_Test_Weighted right action_epoch24": 0.751985559566787, "ENV_Test_Weighted probability to choose the right action:_epoch24": 0.6936022692986735, "ENV_Test_proba_accuracy_epoch24": 0.6936022692986741, "ENV_Test_proba_accuracy_strategy_59_epoch24": 0.7208741237390255, "ENV_Test_proba_accuracy_strategy_19_epoch24": 0.681984529504908, "ENV_Test_proba_accuracy_per_mean_strategy_epoch24": 0.7014293266219667, "ENV_Test_proba_accuracy_per_mean_user_epoch24": 0.7156676991909094, "ENV_Test_proba_accuracy_per_mean_user_and_bot_epoch24": 0.7311071700307894, "ENV_Test_accuracy_epoch24": 0.751985559566787, "ENV_Test_accuracy_strategy_59_epoch24": 0.7939577039274924, "ENV_Test_accuracy_strategy_19_epoch24": 0.7341055341055341, "ENV_Test_accuracy_per_mean_strategy_epoch24": 0.7640316190165133, "ENV_Test_accuracy_per_mean_user_epoch24": 0.7822199927680425, "ENV_Test_accuracy_per_mean_user_and_bot_epoch24": 0.8054054285630959, "_wandb": {"runtime": 9466}}